{"040000HAR415":{"atcoCode":"040000HAR415","naptanCode":"","category":"bus","stopType":"BCT","onStreet":true,"name":"Thame Road Layby","landmark":"","street":"","crossing":"","locality":"Longwick","town":"","suburb":"","coordinates":[-0.86848,51.746275],"indicator":"","properties":{"type":"hailAndRide","stopSubType":"HAR","bearing":"","section":[[-0.8647459,51.7417765],[-0.8639032,51.7414966]],"timingStatus":"OTH","annotatedCoachRef":{}},"stopArea":[],"adminArea":"070","plusbusZone":[],"created":"2024-02-26T12:51:09.000","updated":"2024-02-26T12:51:09.000","status":"active","validity":[]}}