{"0500SSAWS008":{"adminArea":"071","atcoCode":"0500SSAWS008","category":"bus","coordinates":[0.1783736910580586,52.127729069884666],"created":"2003-11-01T00:00:00","crossing":"","indicator":"near","isPublic":false,"landmark":"","locality":"Sawston","name":"Grove Road","naptanCode":"CMBGAPMJ","onStreet":true,"plusbusZone":[],"properties":{"annotatedCoachRef":{},"bearing":"E","section":[],"stopSubType":"MKD","timingStatus":"TIP","type":"marked"},"status":"active","stopArea":[],"stopType":"BCT","street":"","suburb":"","town":"","updated":"2008-04-07T00:00:00","validity":[]}}