{"090002590186":{"adminArea":"074","atcoCode":"090002590186","category":"bus","coordinates":[-3.5642438548245194,54.624761123465035],"created":"2003-03-01T00:00:00.000","crossing":"","indicator":"opp","isPublic":false,"landmark":"","locality":"Salterbeck","name":"Pearl Road","naptanCode":"cumagwtg","onStreet":true,"plusbusZone":[],"properties":{"annotatedCoachRef":{},"bearing":"SW","section":[],"stopSubType":"MKD","timingStatus":"TIP","type":"marked"},"status":"active","stopArea":[],"stopType":"BCT","street":"","suburb":"Salterbeck","town":"Workington","updated":"2016-11-03T00:00:00.000","validity":[]}}