{"1000DWTG3626":{"adminArea":"075","atcoCode":"1000DWTG3626","category":"bus","coordinates":[-1.533616,52.770325],"created":"2006-06-26T00:00:00.000","crossing":"","indicator":"Adj","landmark":"","locality":"Woodville, Swadlincote","name":"Swallow Road","naptanCode":"dbsdgagw","onStreet":true,"plusbusZone":["BURTNOT"],"properties":{"annotatedCoachRef":{},"bearing":"SW","section":[],"stopSubType":"MKD","timingStatus":"TIP","type":"marked"},"status":"active","stopArea":["100G52069"],"stopType":"BCT","street":"","suburb":"","town":"","updated":"2008-10-06T00:00:00.000","validity":[]}}