{"1100DEA10716":{"adminArea":"076","atcoCode":"1100DEA10716","category":"bus","coordinates":[-4.21356,51.03814],"created":"2003-06-12T00:00:00","crossing":"","indicator":"E-bound","landmark":"","locality":"Northam, Devon","name":"Lenards Road","naptanCode":"dvnagawa","onStreet":true,"plusbusZone":[],"properties":{"annotatedCoachRef":{},"bearing":"E","section":[],"stopSubType":"MKD","timingStatus":"OTH","type":"marked"},"status":"active","stopArea":[],"stopType":"BCT","street":"","suburb":"","town":"","updated":"2020-02-25T08:31:54","validity":[]}}