{"1100DEA09070":{"adminArea":"076","atcoCode":"1100DEA09070","category":"bus","coordinates":[-3.50989,50.72176],"created":"2009-01-19T00:00:00","crossing":"","indicator":"W-bound","landmark":"","locality":"Heavitree","name":"Baker Street","naptanCode":"dvngjdat","onStreet":true,"plusbusZone":[],"properties":{"annotatedCoachRef":{},"bearing":"W","section":[],"stopSubType":"MKD","timingStatus":"OTH","type":"marked"},"status":"inactive","stopArea":[],"stopType":"BCT","street":"","suburb":"","town":"","updated":"2025-08-19T16:27:15","validity":[]}}