{"1190TOA10922":{"adminArea":"060","atcoCode":"1190TOA10922","category":"bus","coordinates":[-3.52251,50.47694],"created":"2003-06-12T00:00:00","crossing":"","indicator":"NW-bound","landmark":"","locality":"Babbacombe","name":"Plainmoor","naptanCode":"tbygatm","onStreet":true,"plusbusZone":[],"properties":{"annotatedCoachRef":{},"bearing":"NW","section":[],"stopSubType":"MKD","timingStatus":"OTH","type":"marked"},"status":"inactive","stopArea":[],"stopType":"BCT","street":"","suburb":"","town":"","updated":"2025-08-21T13:31:48","validity":[]}}