{"1200POA10634":{"adminArea":"077","atcoCode":"1200POA10634","category":"bus","coordinates":[-1.97676,50.80447],"created":"2006-06-23T00:00:00","crossing":"","indicator":"SW-bound","landmark":"","locality":"Wimborne Minster, Poole","name":"Onslow Gardens","naptanCode":"dordatwp","onStreet":true,"plusbusZone":[],"properties":{"annotatedCoachRef":{},"bearing":"SW","section":[],"stopSubType":"MKD","timingStatus":"OTH","type":"marked"},"status":"active","stopArea":[],"stopType":"BCT","street":"","suburb":"","town":"","updated":"2025-08-19T13:34:57","validity":[]}}