{"13003658D":{"atcoCode":"13003658D","naptanCode":"duratjwp","category":"bus","stopType":"BCT","onStreet":true,"name":"George Street","landmark":"","street":"","crossing":"","locality":"Seaham","town":"Seaham","suburb":"","coordinates":[-1.339171,54.836445],"indicator":"SE-bound","properties":{"type":"marked","stopSubType":"MKD","bearing":"SE","section":[],"timingStatus":"OTH","annotatedCoachRef":{}},"stopArea":[],"adminArea":"078","plusbusZone":[],"created":"2005-06-02T00:00:00.000","updated":"2026-03-12T08:56:18.829","status":"active","validity":[]}}