{"1400WE1131":{"adminArea":"079","atcoCode":"1400WE1131","category":"bus","coordinates":[0.3534309,50.813867],"created":"2010-09-16T13:23:00.000","crossing":"","indicator":"opp","isPublic":false,"landmark":"","locality":"Pevensey Bay","name":"Seaville Drive","naptanCode":"esudjgad","onStreet":true,"plusbusZone":["EBOURNE"],"properties":{"annotatedCoachRef":{},"bearing":"NE","section":[],"stopSubType":"CUS","timingStatus":"OTH","type":"custom"},"status":"active","stopArea":[],"stopType":"BCT","street":"","suburb":"","town":"","updated":"2018-01-19T12:04:00.000","validity":[]}}