{"1600GLA90909":{"adminArea":"081","atcoCode":"1600GLA90909","category":"bus","coordinates":[-2.5164,51.85213],"created":"2009-08-28T00:00:00","crossing":"","indicator":"opp","landmark":"","locality":"Drybrook","name":"Memorial Hall","naptanCode":"glogpwat","onStreet":true,"plusbusZone":[],"properties":{"annotatedCoachRef":{},"bearing":"S","section":[],"stopSubType":"MKD","timingStatus":"OTH","type":"marked"},"status":"active","stopArea":[],"stopType":"BCT","street":"","suburb":"","town":"","updated":"2017-02-22T10:37:56","validity":[]}}