{"1800WKH3511":{"atcoCode":"1800WKH3511","naptanCode":"","category":"bus","stopType":"BCT","onStreet":true,"name":"Cansfield High School","landmark":"","street":"","crossing":"","locality":"Ashton-in-Makerfield","town":"","suburb":"","coordinates":[-2.646653,53.49376],"indicator":"S-bound","properties":{"type":"hailAndRide","stopSubType":"HAR","bearing":"","section":[[-2.646767,53.494296],[-2.6464441,53.4928866]],"timingStatus":"OTH","annotatedCoachRef":{}},"stopArea":[],"adminArea":"083","plusbusZone":["MNCRPIC"],"created":"2007-11-01T00:00:00.000","updated":"2020-10-02T06:50:05.000","status":"inactive","validity":[]}}