{"1800NEH4421":{"atcoCode":"1800NEH4421","naptanCode":"","category":"bus","stopType":"BCT","onStreet":true,"name":"Binns Nook Road","landmark":"","street":"","crossing":"","locality":"Buckley, Rochdale","town":"","suburb":"","coordinates":[-2.15211,53.628988],"indicator":"NE-bound","properties":{"type":"hailAndRide","stopSubType":"HAR","bearing":"","section":[[-2.1526684,53.628626],[-2.151612,53.6292205]],"timingStatus":"OTH","annotatedCoachRef":{}},"stopArea":[],"adminArea":"083","plusbusZone":[],"created":"2011-01-27T00:00:00.000","updated":"2025-10-23T15:03:15.300","status":"inactive","validity":[]}}