{"1800WK06341":{"adminArea":"083","atcoCode":"1800WK06341","category":"bus","coordinates":[-2.637775,53.53791],"created":"2014-02-13T00:00:00.000","crossing":"","indicator":"opp","landmark":"","locality":"Poolstock","name":"Park Street","naptanCode":"MANPTPDW","onStreet":true,"plusbusZone":[],"properties":{"annotatedCoachRef":{},"bearing":"S","section":[],"stopSubType":"MKD","timingStatus":"OTH","type":"marked"},"status":"active","stopArea":[],"stopType":"BCT","street":"","suburb":"","town":"","updated":"2023-07-21T09:13:23.000","validity":[]}}