{"228000049560":{"adminArea":"036","atcoCode":"228000049560","category":"bus","coordinates":[-0.096116,53.571512],"created":"2003-11-12T00:00:00.000","crossing":"","indicator":"opp","landmark":"","locality":"West Marsh","name":"Beeson Street","naptanCode":"gridgdt","onStreet":true,"plusbusZone":["GRMSBYT"],"properties":{"annotatedCoachRef":{},"bearing":"NW","section":[],"stopSubType":"MKD","timingStatus":"PPT","type":"marked"},"status":"active","stopArea":[],"stopType":"BCT","street":"","suburb":"","town":"Grimsby","updated":"2020-06-04T14:55:05.001","validity":[]}}