{"2400A073410A":{"adminArea":"086","atcoCode":"2400A073410A","category":"bus","coordinates":[1.0876807,51.2607461],"created":"2004-02-25T00:00:00.000","crossing":"","indicator":"o/s","isPublic":false,"landmark":"","locality":"Nackington","name":"Simon Langton Boys' School","naptanCode":"kntgjata","onStreet":true,"plusbusZone":["CNTBE"],"properties":{"annotatedCoachRef":{},"bearing":"N","section":[],"stopSubType":"CUS","timingStatus":"OTH","type":"custom"},"status":"active","stopArea":[],"stopType":"BCT","street":"","suburb":"","town":"","updated":"2014-07-04T15:37:00.000","validity":[]}}