{"2580BRK0012":{"adminArea":"002","atcoCode":"2580BRK0012","category":"bus","coordinates":[-2.478030045,53.761180055],"created":"2006-08-24T00:00:00","crossing":"","indicator":"by","landmark":"","locality":"Brookhouse, Blackburn","name":"Spar","naptanCode":"bladpwm","onStreet":true,"plusbusZone":["BLKB"],"properties":{"annotatedCoachRef":{},"bearing":"S","section":[],"stopSubType":"MKD","timingStatus":"TIP","type":"marked"},"status":"active","stopArea":[],"stopType":"BCT","street":"","suburb":"Brookhouse (Blackburn)","town":"Blackburn","updated":"2009-03-11T15:00:00","validity":[]}}