{"269036026":{"atcoCode":"269036026","naptanCode":"lecdmajd","category":"bus","stopType":"BCT","onStreet":true,"name":"Avoca Close","landmark":"","street":"","crossing":"","locality":"Crown Hills","town":"","suburb":"","coordinates":[-1.076999,52.637251],"indicator":"adj","properties":{"type":"marked","stopSubType":"MKD","bearing":"E","section":[],"timingStatus":"OTH","annotatedCoachRef":{}},"stopArea":[],"adminArea":"027","plusbusZone":[],"created":"2002-12-10T00:00:00.000","updated":"2012-08-06T14:25:42.000","status":"active","validity":[]}}