{"300000159OL":{"adminArea":"093","atcoCode":"300000159OL","category":"bus","coordinates":[-0.861040638,52.259618043],"created":"2004-08-10T00:00:00","crossing":"","indicator":"o/s","landmark":"","locality":"Eastfield Park, Northampton","name":"Eastfield School","naptanCode":"nthajtgj","onStreet":true,"plusbusZone":["NMPTN"],"properties":{"annotatedCoachRef":{},"bearing":"NE","section":[],"stopSubType":"MKD","timingStatus":"OTH","type":"marked"},"status":"active","stopArea":["300G017M"],"stopType":"BCT","street":"","suburb":"Eastfield Park","town":"Northampton","updated":"2011-05-24T08:58:11","validity":[]}}