{"3390BU23":{"adminArea":"039","atcoCode":"3390BU23","category":"bus","coordinates":[-1.1921634,53.0078167],"created":"2003-07-21T00:00:00.000","crossing":"","indicator":"Stop BU23","landmark":"","locality":"Bulwell","name":"Ludford Road","naptanCode":"ntmajgjw","onStreet":true,"plusbusZone":["NTNG"],"properties":{"annotatedCoachRef":{},"bearing":"N","section":[],"stopSubType":"MKD","timingStatus":"OTH","type":"marked"},"status":"active","stopArea":["339GBU32"],"stopType":"BCT","street":"","suburb":"Bulwell","town":"Nottingham","updated":"2010-02-15T11:50:00.000","validity":[]}}