{"3600SOA14127":{"adminArea":"098","atcoCode":"3600SOA14127","category":"bus","coordinates":[-3.12689,51.02764],"created":"2006-02-20T00:00:00","crossing":"","indicator":"W-bound","landmark":"","locality":"Taunton, Somerset","name":"Staplegrove Primary School","naptanCode":"sotdpdtw","onStreet":true,"plusbusZone":[],"properties":{"annotatedCoachRef":{},"bearing":"W","section":[],"stopSubType":"MKD","timingStatus":"OTH","type":"marked"},"status":"active","stopArea":[],"stopType":"BCT","street":"","suburb":"","town":"","updated":"2025-08-14T15:04:13","validity":[]}}