{"370027636":{"adminArea":"099","atcoCode":"370027636","category":"bus","coordinates":[-1.518544704,53.348627171],"created":"2024-10-02T12:00:00","crossing":"","indicator":"27636","landmark":"","locality":"Ecclesall","name":"Dobcroft Road/Dobcroft Close","naptanCode":"37027636","onStreet":true,"plusbusZone":[],"properties":{"annotatedCoachRef":{},"bearing":"N","section":[],"stopSubType":"MKD","timingStatus":"OTH","type":"marked"},"status":"active","stopArea":[],"stopType":"BCT","street":"","suburb":"Ecclesall","town":"Sheffield","updated":"2024-10-02T07:37:38","validity":[]}}