{"370026784":{"adminArea":"099","atcoCode":"370026784","category":"bus","coordinates":[-1.399062198,53.353874387],"created":"2000-01-06T12:00:00","crossing":"","indicator":"","landmark":"","locality":"Normanton Spring","name":"Alport Road/Stanage Rise","naptanCode":"37026784","onStreet":true,"plusbusZone":["SHEFFLD"],"properties":{"annotatedCoachRef":{},"bearing":"N","section":[],"stopSubType":"CUS","timingStatus":"OTH","type":"custom"},"status":"inactive","stopArea":[],"stopType":"BCT","street":"","suburb":"Frecheville","town":"Sheffield","updated":"2010-10-12T01:45:20","validity":[]}}