{"390050336":{"adminArea":"101","atcoCode":"390050336","category":"bus","coordinates":[0.45349,52.07974],"created":"1970-01-01T00:00:00","crossing":"","indicator":"opp","isPublic":false,"landmark":"","locality":"Haverhill","name":"Kestrel Road","naptanCode":"sufgjadm","onStreet":true,"plusbusZone":[],"properties":{"annotatedCoachRef":{},"bearing":"NW","section":[],"stopSubType":"CUS","timingStatus":"OTH","type":"custom"},"status":"active","stopArea":[],"stopType":"BCT","street":"","suburb":"","town":"","updated":"2024-09-17T09:04:09","validity":[]}}