{"410000061243":{"adminArea":"103","atcoCode":"410000061243","category":"bus","coordinates":[-1.4730773,55.0350084],"created":"2011-03-22T15:34:48.000","crossing":"","indicator":"SE-Bound","landmark":"","locality":"West Monkseaton","name":"Drumoyne Gardens","naptanCode":"twrjapmp","onStreet":true,"plusbusZone":[],"properties":{"annotatedCoachRef":{},"bearing":"","section":[[-1.4716208,55.0374609],[-1.4688026,55.0359114]],"stopSubType":"HAR","timingStatus":"PPT","type":"hailAndRide"},"status":"active","stopArea":[],"stopType":"BCT","street":"","suburb":"West Monkseaton","town":"North Tyneside","updated":"2017-05-18T15:40:25.223","validity":[]}}