{"410000012901":{"adminArea":"103","atcoCode":"410000012901","category":"bus","coordinates":[-1.783292,54.93591],"created":"2002-10-28T10:47:01.000","crossing":"","indicator":"NW-Bound","landmark":"","locality":"High Spen","name":"Strothers Road","naptanCode":"twrgwaga","onStreet":true,"plusbusZone":[],"properties":{"annotatedCoachRef":{},"bearing":"NW","section":[],"stopSubType":"MKD","timingStatus":"PPT","type":"marked"},"status":"active","stopArea":[],"stopType":"BCT","street":"","suburb":"High Spen","town":"Gateshead","updated":"2026-01-21T07:16:43.728","validity":[]}}