{"43008440001":{"atcoCode":"43008440001","naptanCode":"nwmpmpdt","category":"bus","stopType":"BCT","onStreet":true,"name":"Kingswinford Health Centre","landmark":"","street":"","crossing":"","locality":"Kingswinford","town":"STOURBRIDGE","suburb":"","coordinates":[-2.160900671747927,52.498866230550426],"indicator":"opp","properties":{"type":"marked","stopSubType":"MKD","bearing":"SE","section":[],"timingStatus":"OTH","annotatedCoachRef":{}},"stopArea":["430G84400"],"adminArea":"105","plusbusZone":[],"created":"2004-08-19T00:00:00","updated":"2026-03-13T00:00:00","status":"active","validity":[]}}