{"43000381502":{"atcoCode":"43000381502","naptanCode":"nwmawmgp","category":"bus","stopType":"BCT","onStreet":true,"name":"Abbeydale Rd","landmark":"","street":"","crossing":"","locality":"Turves Green","town":"BIRMINGHAM","suburb":"","coordinates":[-1.9635888821158332,52.406589216066784],"indicator":"adj","properties":{"type":"marked","stopSubType":"MKD","bearing":"N","section":[],"timingStatus":"OTH","annotatedCoachRef":{}},"stopArea":["430G03815"],"adminArea":"105","plusbusZone":[],"created":"2004-08-19T00:00:00","updated":"2026-03-13T00:00:00","status":"active","validity":[]}}