{"450017531":{"adminArea":"107","atcoCode":"450017531","category":"bus","coordinates":[-1.780276361166547,53.68276460387406],"created":"1999-01-21T00:00:00","crossing":"","indicator":"after","landmark":"","locality":"Fixby","name":"M62 Bridge","naptanCode":"45017531","onStreet":true,"plusbusZone":[],"properties":{"annotatedCoachRef":{},"bearing":"SE","section":[],"stopSubType":"MKD","timingStatus":"OTH","type":"marked"},"status":"active","stopArea":["450G612"],"stopType":"BCT","street":"","suburb":"","town":"Fixby","updated":"2024-01-31T10:06:59","validity":[{"remarks":"","status":"","transferToStop":"","validityEnd":"","validityStart":"1999-01-21"}]}}