{"450016417":{"adminArea":"107","atcoCode":"450016417","category":"bus","coordinates":[-1.264215443726403,53.652214171281614],"created":"1999-01-04T00:00:00","crossing":"","indicator":"","isPublic":false,"landmark":"","locality":"Wentbridge, Pontefract","name":"Old Great North Rd Moor Lane","naptanCode":"45016417","onStreet":true,"plusbusZone":[],"properties":{"annotatedCoachRef":{},"bearing":"N","section":[],"stopSubType":"MKD","timingStatus":"OTH","type":"marked"},"status":"active","stopArea":["450G6971"],"stopType":"BCT","street":"","suburb":"","town":"Wentbridge","updated":"2018-06-12T10:39:14","validity":[{"remarks":"","status":"","transferToStop":"","validityEnd":"","validityStart":"1999-01-04"}]}}