{"450023885":{"adminArea":"107","atcoCode":"450023885","category":"bus","coordinates":[-1.377399373249173,53.67591996431584],"created":"2000-01-04T00:00:00","crossing":"","indicator":"at","isPublic":false,"landmark":"","locality":"Featherstone, West Yorks","name":"Common Side Lane","naptanCode":"45023885","onStreet":true,"plusbusZone":[],"properties":{"annotatedCoachRef":{},"bearing":"W","section":[],"stopSubType":"MKD","timingStatus":"OTH","type":"marked"},"status":"active","stopArea":["450G8039"],"stopType":"BCT","street":"","suburb":"","town":"Featherstone","updated":"2023-12-27T18:22:55","validity":[{"remarks":"","status":"","transferToStop":"","validityEnd":"","validityStart":"2000-01-04"}]}}