{"4600WIA64209":{"adminArea":"108","atcoCode":"4600WIA64209","category":"bus","coordinates":[-2.14753,51.44862],"created":"2009-06-17T00:00:00","crossing":"","indicator":"E-bound","landmark":"","locality":"Chippenham, Wilts","name":"Sainsburys","naptanCode":"wildtdwm","onStreet":true,"plusbusZone":[],"properties":{"annotatedCoachRef":{},"bearing":"E","section":[],"stopSubType":"CUS","timingStatus":"OTH","type":"custom"},"status":"active","stopArea":[],"stopType":"BCT","street":"","suburb":"","town":"","updated":"2015-01-07T09:51:05","validity":[]}}