{"5120WDB22461":{"adminArea":"019","atcoCode":"5120WDB22461","category":"bus","coordinates":[-3.208504872,53.290034334],"created":"2000-01-01T00:00:00","crossing":"","indicator":"nr","isPublic":false,"landmark":"","locality":"Greenfield, Flintshire","name":"Packet House","naptanCode":"flimjta","onStreet":true,"plusbusZone":[],"properties":{"annotatedCoachRef":{},"bearing":"E","section":[],"stopSubType":"MKD","timingStatus":"OTH","type":"marked"},"status":"active","stopArea":[],"stopType":"BCT","street":"","suburb":"","town":"","updated":"2025-06-14T17:15:25","validity":[]}}