{"5530AWB34062":{"adminArea":"030","atcoCode":"5530AWB34062","category":"bus","coordinates":[-3.365432537,51.761007586],"created":"2000-01-01T00:00:00","crossing":"","indicator":"nr","landmark":"","locality":"Penydarren, Merthyr Tydfil","name":"Galon Uchaf Police Station","naptanCode":"mtyawpd","onStreet":true,"plusbusZone":["MERTHYR"],"properties":{"annotatedCoachRef":{},"bearing":"SW","section":[],"stopSubType":"MKD","timingStatus":"OTH","type":"marked"},"status":"active","stopArea":[],"stopType":"BCT","street":"","suburb":"","town":"","updated":"2025-06-28T15:18:53","validity":[]}}