{"60709518":{"adminArea":"114","atcoCode":"60709518","category":"bus","coordinates":[-5.43873,55.85523],"created":"2004-11-30T00:00:00","crossing":"","indicator":"opp","isPublic":false,"landmark":"","locality":"West Tarbert","name":"West Loch Hotel","naptanCode":"54724764","onStreet":true,"plusbusZone":[],"properties":{"annotatedCoachRef":{},"bearing":"NE","section":[],"stopSubType":"CUS","timingStatus":"OTH","type":"custom"},"status":"active","stopArea":["607G4040"],"stopType":"BCT","street":"","suburb":"","town":"","updated":"2012-11-23T14:49:30","validity":[]}}