{"61601090":{"adminArea":"133","atcoCode":"61601090","category":"bus","coordinates":[-3.9397186225631255,55.91434464380062],"created":"2003-08-27T00:00:00","crossing":"","indicator":"Opp","landmark":"","locality":"Greengairs","name":"Coalburn Street","naptanCode":"65234392","onStreet":true,"plusbusZone":[],"properties":{"annotatedCoachRef":{},"bearing":"NE","section":[],"stopSubType":"MKD","timingStatus":"OTH","type":"marked"},"status":"active","stopArea":[],"stopType":"BCT","street":"","suburb":"","town":"GREENGAIRS","updated":"2023-12-12T15:02:54","validity":[]}}