{"6200T00067":{"adminArea":"124","atcoCode":"6200T00067","category":"taxi","coordinates":[-3.250942,55.972717],"created":"2008-01-27T00:00:00.000","crossing":"","indicator":"Near Pennywell Road","isPublic":false,"landmark":"","locality":"West Pilton, Edinburgh","name":"West Pilton Bank","naptanCode":"36298987","onStreet":true,"plusbusZone":["EDINBUR"],"properties":{"type":"taxiRank"},"status":"inactive","stopArea":[],"stopType":"TXR","street":"","suburb":"","town":"","updated":"2010-04-07T00:00:00.000","validity":[]}}