{"6200239510":{"adminArea":"124","atcoCode":"6200239510","category":"bus","coordinates":[-3.163526,55.908914],"created":"2008-01-27T00:00:00.000","crossing":"","indicator":"opp","isPublic":false,"landmark":"","locality":"Gracemount","name":"Little Road","naptanCode":"36237859","onStreet":true,"plusbusZone":["EDINBUR"],"properties":{"annotatedCoachRef":{},"bearing":"N","section":[],"stopSubType":"MKD","timingStatus":"OTH","type":"marked"},"status":"active","stopArea":["620G209110"],"stopType":"BCT","street":"","suburb":"","town":"","updated":"2017-01-13T10:16:50.000","validity":[]}}