{"639006932":{"atcoCode":"639006932","naptanCode":"23232357","category":"bus","stopType":"BCT","onStreet":true,"name":"Pittengullies Brae","landmark":"","street":"","crossing":"","locality":"Milltimber","town":"Aberdeen","suburb":"Culter","coordinates":[-2.252046,57.099176],"indicator":"NE-bound","properties":{"type":"marked","stopSubType":"MKD","bearing":"NE","section":[],"timingStatus":"OTH","annotatedCoachRef":{}},"stopArea":[],"adminArea":"111","plusbusZone":["ABRDEEN"],"created":"2003-07-24T00:00:00.000","updated":"2012-11-23T15:06:00.000","status":"active","validity":[]}}