{"639003162":{"atcoCode":"639003162","naptanCode":"23235757","category":"bus","stopType":"BCT","onStreet":true,"name":"Dunbar Street","landmark":"","street":"","crossing":"","locality":"Old Aberdeen","town":"Aberdeen","suburb":"Old Aberdeen","coordinates":[-2.100964,57.167164],"indicator":"opp","properties":{"type":"marked","stopSubType":"MKD","bearing":"E","section":[],"timingStatus":"OTH","annotatedCoachRef":{}},"stopArea":[],"adminArea":"111","plusbusZone":["ABRDEEN"],"created":"2003-07-21T00:00:00.000","updated":"2021-08-18T17:19:21.315","status":"active","validity":[]}}