{"6500D0426":{"adminArea":"126","atcoCode":"6500D0426","category":"bus","coordinates":[-3.451646,56.064355],"created":"2002-11-26T00:00:00.000","crossing":"","indicator":"Opp","isPublic":false,"landmark":"","locality":"Dunfermline","name":"St Leonard's Bus Depot","naptanCode":"34324623","onStreet":true,"plusbusZone":["DNFRMLE"],"properties":{"annotatedCoachRef":{},"bearing":"SE","section":[],"stopSubType":"MKD","timingStatus":"TIP","type":"marked"},"status":"active","stopArea":["650GD0425"],"stopType":"BCT","street":"","suburb":"","town":"","updated":"2017-03-09T11:41:15.000","validity":[]}}