{"6500D0663":{"adminArea":"126","atcoCode":"6500D0663","category":"bus","coordinates":[-3.522323,56.084008],"created":"2002-11-26T00:00:00.000","crossing":"","indicator":"adj","landmark":"","locality":"Gowkhall","name":"Dean Ridge","naptanCode":"34325432","onStreet":true,"plusbusZone":["DNFRMLE"],"properties":{"annotatedCoachRef":{},"bearing":"SE","section":[],"stopSubType":"MKD","timingStatus":"PPT","type":"marked"},"status":"active","stopArea":["650GD0662"],"stopType":"BCT","street":"","suburb":"","town":"","updated":"2009-10-12T00:00:00.000","validity":[]}}