{"66902340072":{"adminArea":"125","atcoCode":"66902340072","category":"bus","coordinates":[-3.644483,56.006456],"created":"2008-01-27T00:00:00.000","crossing":"","indicator":"at","landmark":"","locality":"Boness","name":"Mason Coaches Depot","naptanCode":"32526468","onStreet":true,"plusbusZone":["LNLTHGW"],"properties":{"annotatedCoachRef":{},"bearing":"NE","section":[],"stopSubType":"MKD","timingStatus":"OTH","type":"marked"},"status":"active","stopArea":["669G2340072"],"stopType":"BCT","street":"","suburb":"","town":"","updated":"2011-06-28T14:12:47.000","validity":[]}}