{"69001200":{"adminArea":"115","atcoCode":"69001200","category":"bus","coordinates":[-2.900277,55.543762],"created":"2005-10-03T00:00:00.000","crossing":"","indicator":"At","isPublic":false,"landmark":"","locality":"Bowhill, Selkirk","name":"Bowhill Junction","naptanCode":"72726972","onStreet":true,"plusbusZone":[],"properties":{"annotatedCoachRef":{},"bearing":"NW","section":[],"stopSubType":"CUS","timingStatus":"PPT","type":"custom"},"status":"active","stopArea":[],"stopType":"BCT","street":"","suburb":"","town":"Bowhill Selkirk","updated":"2025-02-18T10:55:46.001","validity":[]}}