{"9300BWD":{"adminArea":"146","atcoCode":"9300BWD","category":"ferry","coordinates":[-3.06161231607,54.35307787083],"created":"2010-07-16T17:03:00","crossing":"","indicator":"","isPublic":false,"landmark":"","locality":"Brantwood","name":"Brantwood (Coniston) Ferry Landing","naptanCode":"","onStreet":false,"plusbusZone":[],"properties":{"annotatedFerryRef":{"FerryRef":"BWD","Location":{"Easting":"331099","GridType":"UKOS","Northing":"495802"},"Name":"Brantwood (Coniston) Ferry Landing","RevisionNumber":"0"},"type":"accessArea"},"status":"active","stopArea":["930GBWD"],"stopType":"FER","street":"","suburb":"","town":"","updated":"2013-01-02T16:42:00","validity":[]}}