{"9400ZZMAPLL":{"adminArea":"147","atcoCode":"9400ZZMAPLL","category":"metro","coordinates":[-2.25036885262,53.37369326139],"created":"2014-09-12T11:50:00","crossing":"","indicator":"","isPublic":false,"landmark":"","locality":"Peel Hall","name":"Peel Hall (Manchester Metrolink)","naptanCode":"mantwjgp","onStreet":false,"plusbusZone":["MNCRPIC"],"properties":{"annotatedMetroRef":{},"type":"accessArea"},"status":"active","stopArea":["940GZZMAPLL"],"stopType":"MET","street":"","suburb":"","town":"","updated":"2021-04-27T12:13:28","validity":[]}}