{"s11-penistone-road-rowley-lane-j--i-school":[{"description":"Penistone Road - Rowley Lane J & I School","destination":"Rowley Lane J & I School","endDate":"2026-05-23","filename":"Y_FG_FWYO_S11_1.xml","lastModified":"2026-04-23T09:55:10","lineId":["SL49"],"mode":"bus","name":["S11"],"operators":["FWYO"],"origin":"Penistone Road","publicUse":"false","region":"Y","routes":[{"description":"King James's School - Rowley Lane J I & N School","direction":["outbound","outbound","outbound","outbound","outbound","outbound","outbound","outbound","outbound","outbound","outbound","outbound","outbound","outbound","outbound","outbound","outbound","outbound","outbound","outbound","outbound","outbound","outbound","outbound","outbound","outbound"],"distance":[2198,383,426,1596,267,284,137,213,366,540,320,387,643,201,259,297,458,236,492,622,257,209,969,129,117,153],"routeId":"RT138","routeLinkIds":["RL3663","RL3664","RL3665","RL3666","RL3667","RL3668","RL3669","RL3670","RL3671","RL3672","RL3673","RL3674","RL3675","RL3676","RL3677","RL3678","RL3679","RL3680","RL3681","RL3682","RL3683","RL3684","RL3685","RL3686","RL3687","RL3688"],"stopPoints":["450029163","450016775","450016772","450016771","450018765","450021108","450021105","450018767","450028284","450028285","450018779","450018776","450018775","450016768","450016766","450016764","450017226","450020664","450024122","450028810","450021602","450021601","450018800","450018790","450018788","450018787","9991AM018"],"tracks":"arfheBxwgiBE@m@cMxRkJtIiItRoE~PXv\\j@fNmFnQcMvQuUjF{G^aCTmCn@}F}@cHgQoUag@it@se@{w@yJkSiHuR_Ny^{AgG{AoF}B_IaE_NwI}_@cF_]yEq_@qGqs@mIcyAz@{d@N{HdEkzB@}@X{N`G_uA~BuThJkj@bMue@~Xws@`NsVnBqDvIoMvEaHbaAaxApN}SfMwT`EgHhSse@t@eM_\\{yAw_AjZqBp@eCv@mt@~V??\\|D]}DyLdEqj@rJmbAv]mfAbg@yA\\aAd@??h@jEi@kEkWvL}@n@s\\zUko@dr@ek@tm@mI`JoHbH}JrIwUbQ??v@hEw@iEc]~VqI|HyO~PwCdEkCfEeBhCiBhDaJxRuDjJgIpSg@zAYv@{@dCyAdEYx@jBxB~E~GbEfMzCxJ?fGhEbU|VbgBtEj\\hZlpAzUhrAjFdh@hNtvBTxDXnFvIt|AtB~^n@rGbNxtAfAnKrSjpAnMfp@d@hBhGfVjZfv@t@nBpn@pbB|CvTfE`Z??tBmAuBlAvBnOFfG@bBJvN}AnLsIrMcAvAmNvJah@`m@sDpE}BvBe@bNyAvBQI??i@~Dh@_EaIkEcMjHkKjHmP~Noq@fy@mSpVkDzE??|AjE}AkEsDhFoJe\\yQwn@wA{G??sAjArAkAqG_Zk]pe@oYz`@kRbY??xA|DyA}DqWb`@eNjZqLjYsZpe@cJg^e[waB??{BbBzBcBgW}sAsuAw{Emd@{{A{GuU??oAvAnAwAwXm`A{K_c@uJsi@eKm~@}Cyv@?yA??W?V??sVnBwe@h]|Czx@kUh\\mVVa@pWy_@bMwRlDsC??Q}@P|@nj@uc@nUmEp_@b@ve@bA_@}b@kBwT_g@mzDmMocAsCdAmDvA}HbC??f@fGg@gG_AZgKdDuMpDmFpAcE`A{FzAiA\\cJxBuMjDsMhD}FtA??`@bHa@cHaE`AcHbBuJvCwHbCuDhA{DdCaCtAmOxK{CzCaS~QiQvPiJ~I??fArEgAsEoEfEoTdSgJxH_CrHoFbFoC|BaEdDmAnAwBpB_DrCaCpCmEjFgDrEwG~JcHhLaE|FeCdE{AdCyG~Jw@pA??|@tB}@uBaC`EyC`GsEzJqApDkArCy@hCQp@oHjLaAjEw@|EqAlHYxCw@tDg@vA}AfDgAqKu@gI_@sG]wGWiFMsBAoDDeGFsEWyKUaXAiVG}LF}Ol@e[XoOlBsa@^{Ih@yJj@oJl@qL`@_E??{@]z@\\vCmZxCoR|BqKxFiTpHaPhW{`@pL_QrFsI|AwB??s@sBr@rBfDyErAmBpC}DxV}]nKeOjG{ItBqD`OqWpS}g@jDN`CHjBU`Ba@bk@oTxXqHpL_DrOmDrMsA|E\\??HqDIpD`e@jDbDR``@`TzF\\|J{EhVaGp^{IxWqG~c@uR~X{LbM{HtAgApB}BxEaIzCgFxEwJjCcJbAeEbBgFQqFmBwk@??u@Jt@KKkDa@e^fEyRrB_BlXgTh[qV~K}OpRwZ??e@iAd@hAhE}G|F}OzAmZx@eo@NeVVee@?uDBcM???BRka@?w[?wG?SR{aA??R_X?_Nf@we@f@oU?g@R_]nAo_@~Cod@nFkp@z@_Nz@kMf@_NnAc`@nAsXRgEf@gEf@{EnA_I~CwL~C_IbBoFrI{OzT_l@~H_SrDsIz@oAjC{Ez@cBvG_IfJ_N~MkRzEgJbBgEz@kCz@sI??S??SS??S?SS??S?S?S?S?S?S?SR??S?SR??SRSR?R?R?R??RRR?R?RR??Rf@Rz@Rz@z@z@z@?nAjCzJvBfJbGbV\\[??|A_B}A~A~Sny@vKhd@??fBcBgBbBd@lB|Xtx@~FzP??MLnAfEz@~Cf@bBnAbG?Rf@bBRf@?f@RbBRnARvB?nA?z@?jC?jCg@rIg@fJ?~CSjC?~HRvGRf@f@bQRf@??kCf@_Df@"},{"description":"Rowley Lane J I & N School - Moldgreen","direction":["inbound","inbound","inbound","inbound","inbound","inbound","inbound","inbound","inbound","inbound","inbound","inbound","inbound","inbound","inbound","inbound","inbound","inbound","inbound","inbound","inbound","inbound","inbound","inbound","inbound","inbound","inbound","inbound","inbound","inbound","inbound","inbound","inbound","inbound","inbound","inbound","inbound","inbound","inbound","inbound"],"distance":[272,184,224,212,371,411,254,252,239,285,251,466,203,166,938,279,232,303,311,296,247,172,352,1392,267,284,137,213,366,289,258,320,178,174,155,312,358,285,439,172],"routeId":"RT139","routeLinkIds":["RL3689","RL3690","RL3691","RL3692","RL3693","RL3694","RL3695","RL3696","RL3697","RL3698","RL3699","RL3700","RL3701","RL3702","RL3703","RL3704","RL3705","RL3706","RL3707","RL3708","RL3709","RL3710","RL3711","RL3712","RL3713","RL3714","RL3715","RL3716","RL3717","RL3718","RL3719","RL3720","RL3721","RL3722","RL3723","RL3724","RL3725","RL3726","RL3727","RL3728"],"stopPoints":["9991AM018","450018785","450018783","450028528","450016775","450016772","450016771","450021602","450021601","450018800","450020670","450020669","450026488","450026489","450026492","450028810","450020666","450020665","450020663","450016762","450016763","450016765","450016767","450016769","450018765","450021108","450021105","450018767","450028284","450028285","450029556","450018779","450018776","450026827","450025590","450017227","450017228","450017229","450017230","450017231","450017232"],"tracks":"okhheBn`ngBg@?sD?kC{@{@g@g@S{@kC{@sDSkC?{@?{Ez@{EbB_DbBcB??~CcBbBSjHS??SjC?~HRvGRf@f@bQRf@~CvQvBbGjCrIrIzObVfT??fEfEbLbQz@jCnAjCz@rDz@rDz@rDvBnPz@nFRvBbBbGbBvGjCzJvBbGjHbV??fErNvBjHbB~Hf@~Cz@rDRzE?vB?jCSvGoAbVoA~Rg@bL?jCS~CcBfc@nAj\\RnA??S?vBvQf@jC~CvQRbB~CvLf@vBz@~CnAzEbGrS??gYrI_XfJ{@R??_IvB_Df@cGbBwGf@_IbB_IvB_NrD_NrD_SjHoAf@g@RkCz@_IrDcQjHwLnFS?wQjH{@f@gTzJ{EjC??c[fO{E~CwBvBoAz@oKrIoPfOkHjHcBbBwLjM{EzEgEzEgJnKsDrDcBjCgErDwBjCcLrNS?oFnFoAz@_IjHsIbGkHnFgE~CoAz@??{JjH{E~CwBvBcBbBcGzEgErDoFnFcGbG??S_DSgJSoF?oF?sI?_ISoA?oFg@_ISkHSoAS_Dg@cQ?S{@gY???{@ScB?wBg@oK?sDRwB?cBRgERoAR{@RcBbB{Ez@wBnAoArX_S~MoKnFgEnF{EzEcGvBwBnAoArNwVnAkC??~H{ObBcGR{@z@cGRgJ?gEnAsl@RoA?{ORkk@?sD?g@Rwo@???w[?wG?SR{aA??_Ng@{OkCkRsDcBg@_IoAcBg@cG{@??SrDoAzJ?RoA~H{@fE??oAnFcBjHg@nAsDnKg@nAsD~HcBrDg@nAoAvB{@bBoFnKSRgJnPoF~HSRkHbLoKbQg@f@wB~C_DzEwGzJg@z@wBrD??_DrDcGnKoAvBgEvG{EjHsDbGcGfJ{@z@{@nASf@oAnA_DrDg@RsDrDwBz@{@RoFvBsDnAwBf@wBf@kMf@sN~CsIvBkWvG_DnAwBnAkCvBwBbBSRcBbBcBnAg@z@{@f@??f@f@?RRR?f@RR?RRR?f@?RRf@?R?R?f@?R?f@?R?f@SR?f@?R?RSf@?RSR?RSRSRbBrDz@nARf@bB~CnAnARRz@z@f@f@RRnAf@z@RnARf@Sz@?bB?bBRnAf@bBf@z@z@??nAz@bBvBvB~CbGjRvBjHnAjCz@bBvBfEvB~CRRjH~HjHvG~CjCjCrDjHfJzEjHfEnFvBvB??bBvBzEzEf@RfJjH??f@cBf@{@f@g@f@Sf@?f@?f@?RRz@f@f@z@bGgJnFwLbB{EbG{YvBoK??f@gEvG{YRoAz@wBf@wBz@wBz@oARSnAcBnAcBvBkC~CwBrDcBf@SbB{@~Cg@vB?vB?zEf@nARbBRvBnAjCnAz@z@nAnAf@nARf@Rz@nArDz@bGf@bB??sX~RoAnA{@vBcBzESbBSz@SnASfE?bBSvB?rDf@nK?vBRbBz@b[?Rf@bQR~CRnA??oAfEoArDoAzE{@~CoFzJSf@{JbQoAz@oAf@kM~H{JfEwQfJcLbGgOfEwL~C{@f@_NfEwLjCcGnAsDz@sDz@oFnAsDz@gEbBoFvBg@RcBf@wB?g@SoAS_DcB{@g@oF_DsDwB{@g@cB{@g@g@oASwGoAsDg@w[wBwBS??oA?_DSwBRwBz@_Df@cBf@oARkWvGg@?{TbGkCz@g@R_IbBsDz@gYjHSRgEnASRkCf@sDnA??cBrDg@bBSz@wBnFg@z@GW??jBxCkByC}HxRaOpWuBpDkGzIoKdOyV|]qC|DsAlBeGpIaBfC??rAjDsAkDqCjEqL~PiWz`@qH`PyFhT}BpKyCnRyDl`@m@pLk@nJi@xJ_@zIm@jM??tEz@uE{@_AfSYnOm@d[G|OF|L@hVT`XVxKGrEhBtF|BtAvAt@|@b@vAN~@Gl@G~@s@`BiD`CgFxBgEbB_ElBiErBsErBiDrBkDJQ??CEBD`DiFfDuFfEwGdFyHdR_ZtCsDlDqEjBgCtC_D`BcBbD{ChAaAdB}ArCmCtD}C|GkBfJyHnTeSbKwJ??u@{Ct@zCtDoDhQwP`S_RzC{ClOyK`CuAzDeCtDiAvHcCtJwCbHcBpHgB??UwDTvDlCo@rMiDtMkDbJyBhA]zF{AbEaAlFqAtMqDrC}@??]kE\\jErFgB|J_DlDwArCeAfEyA~@]zD_BtIkF`GuDnGwFdE{CvEoExDoE~BoC`CeDfHcLzCiGhDaIzEcMxE_OzAyEzEkOdCqHzDmM??{@eAz@dAnFkQbHuSjBxB~E~GbEfMzCxJ?fGhEbU|VbgBtEj\\hZlpAzUhrAjFdh@hNtvBTxDXnFvIt|AtB~^n@rGbNxtAfAnKrSjpAnMfp@d@hBhGfVjZfv@t@nBpn@pbB|CvTfE`Z??tBmAuBlAvBnOFfG@bBJvN}AnLsIrMcAvAmNvJah@`m@sDpE}BvBe@bNyAvBQI??i@~Dh@_EaIkEcMjHkKjHmP~Noq@fy@mSpVkDzE??|AjE}AkEsDhFoJe\\yQwn@wA{G??sAjArAkAqG_Zk]pe@oYz`@kRbY??xA|DyA}DqWb`@eNjZqLjYsZpe@cJg^e[waB??{BbBzBcBgW}sAiu@kiC??w@|@v@}@i_@kqAmd@{{A{GuU??oAvAnAwAwXm`A{K_c@uJsi@eKm~@}Cyv@?yA??W?V??sVnBwe@wp@{GoJU??EbIDcIqDIkEd@mDrD}OpPoNDq@M{A]q@a@uD{CcBiB{GqMgByA??]~A\\_BeLiJeBmAk@E}AHmFMmEn@@bFJtIj@hSd@lPv@bRNbC??vD}@wD|@r@xLZpHj@|L|@bSdA|Tz@pOhDvn@rEn|@VvFLhClAxV`B~]??hDo@iDn@f@rK`Bf]zBtg@^nIjC|eAb@zPF|q@Bf_@YdQQ`L[|J[bI??vEp@wEq@GhB_@`Je@tMi@nKq@vLiArPiAnOoAtL}@vKo@hGo@dHUbC{@jGo@vEsN~kA[fC]nC??FAoAfJcBrNg@fEwGvj@wGjf@kCjR_DjW{@jHwBbQwBfToA~M?bB?RoAjWg@jRSrISvB?jM?fTRnPRbGRbGRrSRrD?nARfEf@nK??z@vQnAfObB~Wf@rDnA~Mz@jHbB~Mf@fEbBnKvBfORRvBjM"}],"servicedOrganisations":{"ORG1":{"name":"Schools1","workingDays":[{"description":"Schools1","endDate":"2025-10-24","startDate":"2025-09-01"},{"description":"Schools1","endDate":"2025-12-19","startDate":"2025-11-03"},{"description":"Schools1","endDate":"2026-02-13","startDate":"2026-01-05"},{"description":"Schools1","endDate":"2026-04-02","startDate":"2026-02-23"},{"description":"Schools1","endDate":"2026-05-22","startDate":"2026-04-13"},{"description":"Schools1","endDate":"2026-07-21","startDate":"2026-06-01"}]},"SCH":{"name":"School Days","workingDays":[{"description":"School Days","endDate":"2025-10-24","startDate":"2025-09-01"},{"description":"School Days","endDate":"2024-12-20","startDate":"2024-11-04"},{"description":"School Days","endDate":"2025-02-14","startDate":"2025-01-06"},{"description":"School Days","endDate":"2025-04-04","startDate":"2025-02-24"},{"description":"School Days","endDate":"2025-05-23","startDate":"2025-04-22"},{"description":"School Days","endDate":"2025-07-22","startDate":"2025-06-02"},{"description":"School Days","endDate":"2025-12-19","startDate":"2025-11-03"},{"description":"School Days","endDate":"2026-02-13","startDate":"2026-01-05"},{"description":"School Days","endDate":"2026-04-02","startDate":"2026-02-23"},{"description":"School Days","endDate":"2026-05-22","startDate":"2026-04-13"},{"description":"School Days","endDate":"2026-07-21","startDate":"2026-06-01"}]},"YSBA":{"name":"HaxSch01","workingDays":[{"description":"HaxSch01","endDate":"2025-10-24","startDate":"2025-09-01"},{"description":"HaxSch01","endDate":"2025-12-19","startDate":"2025-11-03"},{"description":"HaxSch01","endDate":"2026-02-13","startDate":"2026-01-05"},{"description":"HaxSch01","endDate":"2026-04-02","startDate":"2026-02-23"},{"description":"HaxSch01","endDate":"2026-05-22","startDate":"2026-04-13"},{"description":"HaxSch01","endDate":"2026-07-21","startDate":"2026-06-01"}]},"YSBB":{"name":"BfdSch01","workingDays":[{"description":"BfdSch01","endDate":"2025-10-24","startDate":"2025-09-01"},{"description":"BfdSch01","endDate":"2025-12-19","startDate":"2025-11-03"},{"description":"BfdSch01","endDate":"2026-02-13","startDate":"2026-01-05"},{"description":"BfdSch01","endDate":"2026-04-02","startDate":"2026-02-23"},{"description":"BfdSch01","endDate":"2026-05-22","startDate":"2026-04-20"},{"description":"BfdSch01","endDate":"2026-07-21","startDate":"2026-06-01"}]},"YSBU":{"name":"HudSch01","workingDays":[{"description":"HudSch01","endDate":"2025-10-24","startDate":"2025-09-01"},{"description":"HudSch01","endDate":"2025-12-19","startDate":"2025-11-03"},{"description":"HudSch01","endDate":"2026-02-13","startDate":"2026-01-05"},{"description":"HudSch01","endDate":"2026-04-02","startDate":"2026-02-23"},{"description":"HudSch01","endDate":"2026-05-22","startDate":"2026-04-20"},{"description":"HudSch01","endDate":"2026-07-21","startDate":"2026-06-01"}]}},"startDate":"2026-05-05","timetables":{"RT138":[{"activities":[],"destinationDisplay":"Rowley Lane J I & N","direction":"outbound","dynamicDestinationDisplay":[],"lineId":"SL49","note":[],"routeLinkId":["RL3663","RL3664","RL3665","RL3666","RL3667","RL3668","RL3669","RL3670","RL3671","RL3672","RL3673","RL3674","RL3675","RL3676","RL3677","RL3678","RL3679","RL3680","RL3681","RL3682","RL3683","RL3684","RL3685","RL3686","RL3687","RL3688"],"runtimes":["PT4M0S","PT0M0S","PT1M0S","PT3M0S","PT0M0S","PT1M0S","PT1M0S","PT1M0S","PT1M0S","PT3M0S","PT1M0S","PT2M0S","PT3M0S","PT0M0S","PT2M0S","PT1M0S","PT2M0S","PT1M0S","PT2M0S","PT2M0S","PT1M0S","PT1M0S","PT7M0S","PT1M0S","PT1M0S","PT1M0S"],"schedules":[{"dayShift":[0],"departures":["08:06:00"],"profiles":{"holidays":{"notRunning":["ChristmasDay","BoxingDay","GoodFriday","NewYearsDay","LateSummerBankHolidayNotScotland","MayDay","EasterMonday","SpringBank","ChristmasDayHoliday","BoxingDayHoliday","NewYearsDayHoliday","OtherPublicHoliday","ChristmasEve","NewYearsEve",{"date":"2023-05-08","description":"CoronationBankHoliday"}]},"regular":["Monday"],"servicedOrganisations":{"running":[{"WorkingDays":{"ServicedOrganisationRef":"YSBU"}}]}}},{"dayShift":[0],"departures":["08:06:00"],"profiles":{"holidays":{"notRunning":["ChristmasDay","BoxingDay","GoodFriday","NewYearsDay","LateSummerBankHolidayNotScotland","MayDay","EasterMonday","SpringBank","ChristmasDayHoliday","BoxingDayHoliday","NewYearsDayHoliday","OtherPublicHoliday","ChristmasEve","NewYearsEve",{"date":"2023-05-08","description":"CoronationBankHoliday"}]},"regular":["Tuesday"],"servicedOrganisations":{"running":[{"WorkingDays":{"ServicedOrganisationRef":"YSBU"}}]}}},{"dayShift":[0],"departures":["08:06:00"],"profiles":{"holidays":{"notRunning":["ChristmasDay","BoxingDay","GoodFriday","NewYearsDay","LateSummerBankHolidayNotScotland","MayDay","EasterMonday","SpringBank","ChristmasDayHoliday","BoxingDayHoliday","NewYearsDayHoliday","OtherPublicHoliday","ChristmasEve","NewYearsEve",{"date":"2023-05-08","description":"CoronationBankHoliday"}]},"regular":["Wednesday"],"servicedOrganisations":{"running":[{"WorkingDays":{"ServicedOrganisationRef":"YSBU"}}]}}},{"dayShift":[0],"departures":["08:06:00"],"profiles":{"holidays":{"notRunning":["ChristmasDay","BoxingDay","GoodFriday","NewYearsDay","LateSummerBankHolidayNotScotland","MayDay","EasterMonday","SpringBank","ChristmasDayHoliday","BoxingDayHoliday","NewYearsDayHoliday","OtherPublicHoliday","ChristmasEve","NewYearsEve",{"date":"2023-05-08","description":"CoronationBankHoliday"}]},"regular":["Thursday"],"servicedOrganisations":{"running":[{"WorkingDays":{"ServicedOrganisationRef":"YSBU"}}]}}},{"dayShift":[0],"departures":["08:06:00"],"profiles":{"holidays":{"notRunning":["ChristmasDay","BoxingDay","GoodFriday","NewYearsDay","LateSummerBankHolidayNotScotland","MayDay","EasterMonday","SpringBank","ChristmasDayHoliday","BoxingDayHoliday","NewYearsDayHoliday","OtherPublicHoliday","ChristmasEve","NewYearsEve",{"date":"2023-05-08","description":"CoronationBankHoliday"}]},"regular":["Friday"],"servicedOrganisations":{"running":[{"WorkingDays":{"ServicedOrganisationRef":"YSBU"}}]}}}],"sequenceNumber":[],"stopPoints":["450029163","450016775","450016772","450016771","450018765","450021108","450021105","450018767","450028284","450028285","450018779","450018776","450018775","450016768","450016766","450016764","450017226","450020664","450024122","450028810","450021602","450021601","450018800","450018790","450018788","450018787","9991AM018"],"timingStatuses":["PTP","OTH","OTH","OTH","OTH","PTP","OTH","OTH","OTH","OTH","OTH","OTH","OTH","OTH","OTH","OTH","OTH","OTH","OTH","PTP","OTH","OTH","PTP","OTH","OTH","OTH","PTP"],"vehicle":"","waitTimes":["","","","","","","","","","","","","","","","","","","","","","","","","","",""]}],"RT139":[{"activities":[],"destinationDisplay":"Moldgreen","direction":"inbound","dynamicDestinationDisplay":[],"lineId":"SL49","note":[],"routeLinkId":["RL3689","RL3690","RL3691","RL3692","RL3693","RL3694","RL3695","RL3696","RL3697","RL3698","RL3699","RL3700","RL3701","RL3702","RL3703","RL3704","RL3705","RL3706","RL3707","RL3708","RL3709","RL3710","RL3711","RL3712","RL3713","RL3714","RL3715","RL3716","RL3717","RL3718","RL3719","RL3720","RL3721","RL3722","RL3723","RL3724","RL3725","RL3726","RL3727","RL3728"],"runtimes":["PT1M0S","PT0M0S","PT0M0S","PT1M0S","PT1M0S","PT0M0S","PT1M0S","PT1M0S","PT0M0S","PT1M0S","PT0M0S","PT2M0S","PT0M0S","PT1M0S","PT2M0S","PT1M0S","PT2M0S","PT1M0S","PT2M0S","PT1M0S","PT1M0S","PT1M0S","PT1M0S","PT3M0S","PT1M0S","PT1M0S","PT1M0S","PT1M0S","PT1M0S","PT2M0S","PT1M0S","PT1M0S","PT1M0S","PT1M0S","PT1M0S","PT2M0S","PT2M0S","PT1M0S","PT3M0S","PT1M0S"],"schedules":[{"dayShift":[0],"departures":["15:33:00"],"profiles":{"holidays":{"notRunning":["ChristmasDay","BoxingDay","GoodFriday","NewYearsDay","LateSummerBankHolidayNotScotland","MayDay","EasterMonday","SpringBank","ChristmasDayHoliday","BoxingDayHoliday","NewYearsDayHoliday","OtherPublicHoliday","ChristmasEve","NewYearsEve",{"date":"2023-05-08","description":"CoronationBankHoliday"}]},"regular":["Monday"],"servicedOrganisations":{"running":[{"WorkingDays":{"ServicedOrganisationRef":"YSBU"}}]}}},{"dayShift":[0],"departures":["15:35:00"],"profiles":{"holidays":{"notRunning":["ChristmasDay","BoxingDay","GoodFriday","NewYearsDay","LateSummerBankHolidayNotScotland","MayDay","EasterMonday","SpringBank","ChristmasDayHoliday","BoxingDayHoliday","NewYearsDayHoliday","OtherPublicHoliday","ChristmasEve","NewYearsEve",{"date":"2023-05-08","description":"CoronationBankHoliday"}]},"regular":["Tuesday"],"servicedOrganisations":{"running":[{"WorkingDays":{"ServicedOrganisationRef":"YSBU"}}]}}},{"dayShift":[0],"departures":["15:35:00"],"profiles":{"holidays":{"notRunning":["ChristmasDay","BoxingDay","GoodFriday","NewYearsDay","LateSummerBankHolidayNotScotland","MayDay","EasterMonday","SpringBank","ChristmasDayHoliday","BoxingDayHoliday","NewYearsDayHoliday","OtherPublicHoliday","ChristmasEve","NewYearsEve",{"date":"2023-05-08","description":"CoronationBankHoliday"}]},"regular":["Wednesday"],"servicedOrganisations":{"running":[{"WorkingDays":{"ServicedOrganisationRef":"YSBU"}}]}}},{"dayShift":[0],"departures":["15:35:00"],"profiles":{"holidays":{"notRunning":["ChristmasDay","BoxingDay","GoodFriday","NewYearsDay","LateSummerBankHolidayNotScotland","MayDay","EasterMonday","SpringBank","ChristmasDayHoliday","BoxingDayHoliday","NewYearsDayHoliday","OtherPublicHoliday","ChristmasEve","NewYearsEve",{"date":"2023-05-08","description":"CoronationBankHoliday"}]},"regular":["Thursday"],"servicedOrganisations":{"running":[{"WorkingDays":{"ServicedOrganisationRef":"YSBU"}}]}}},{"dayShift":[0],"departures":["15:35:00"],"profiles":{"holidays":{"notRunning":["ChristmasDay","BoxingDay","GoodFriday","NewYearsDay","LateSummerBankHolidayNotScotland","MayDay","EasterMonday","SpringBank","ChristmasDayHoliday","BoxingDayHoliday","NewYearsDayHoliday","OtherPublicHoliday","ChristmasEve","NewYearsEve",{"date":"2023-05-08","description":"CoronationBankHoliday"}]},"regular":["Friday"],"servicedOrganisations":{"running":[{"WorkingDays":{"ServicedOrganisationRef":"YSBU"}}]}}}],"sequenceNumber":[],"stopPoints":["9991AM018","450018785","450018783","450028528","450016775","450016772","450016771","450021602","450021601","450018800","450020670","450020669","450026488","450026489","450026492","450028810","450020666","450020665","450020663","450016762","450016763","450016765","450016767","450016769","450018765","450021108","450021105","450018767","450028284","450028285","450029556","450018779","450018776","450026827","450025590","450017227","450017228","450017229","450017230","450017231","450017232"],"timingStatuses":["PTP","OTH","OTH","OTH","OTH","OTH","OTH","OTH","OTH","PTP","OTH","OTH","OTH","OTH","OTH","PTP","OTH","OTH","OTH","OTH","OTH","OTH","PTP","OTH","OTH","PTP","OTH","OTH","OTH","OTH","OTH","OTH","OTH","PTP","OTH","OTH","OTH","OTH","OTH","OTH","PTP"],"vehicle":"","waitTimes":["","","","","","","","","","","","","","","","","","","","","","","","","","","","","","","","","","","","","","","","",""]}]},"vehicles":{"":{"description":""}},"vias":[]}]}