{"t21-aberystwyth-tregaron":[{"filename":"_JAEV_T21_Aberystwyth-Tregaron_7_20250102_EVAT021.json","mode":"bus","region":"W","lineId":["SL1"],"name":["T21"],"origin":"Aberystwyth","destination":"Tregaron","vias":["Pontrhydygroes & Llanafan"],"description":"Aberystwyth - Tregaron via Pontrhydygroes & Llanafan","operators":["JAEV"],"lastModified":"2026-04-08T17:08:00","publicUse":"true","startDate":"2025-01-02","endDate":"","routes":[{"routeId":"RT1","routeLinkIds":["RL1","RL2","RL3","RL4","RL5","RL6","RL7","RL8","RL9"],"description":"Wenallt - Talbot Hotel","stopPoints":["5230WDB47548","5230CGX16406","5230CGX16423","5230AWD71036","5230AWD71034","5230CGX16407","5230CGX16417","5230CGX16484","5230WDB47545","5230AWD71030"],"distance":[1656,29,3201,2462,837,888,1830,6301,3382],"tracks":"u~zxbBljzoFnKiOf[ea@bb@en@dLmY~ZslC`BiNzU_bBjOqgCxGsp@@eqCv@wQtOosAunAcPefDk_AqMkCqjAnTqItEiFxDn@pEUpEc@tC??yA|JdBqLVaBTqEo@qEhFyDpIuEpjAoTpMjCdfDj_AtnAbP~Dkk@`V{mA`Jsp@eKs|@cAyIaAy[hDcQzUmZxSrVzTpSlyAlh@dItCzENfm@{Ddx@{`@vPgO~Qm]rLaHhFqAlj@hAbRcCnF}ClT_U~Q_j@xCsSsBy^DiIjBsHbJ{R`^_h@bNqMro@mNrg@dBpHmAnl@ef@ri@_]je@_j@he@geAxP_ZdSkWbUyRxl@eXjIwDjf@a[do@aSvb@mE|q@fC~AP??dKfArT`CxVaIhg@}l@dReKhl@qAtl@rBpI}At\\aTlc@_f@fQoN~YeOrd@_Mps@oXjTeKrEcEpFcInCoHxBgJpBaLhAcRpAkRp@mRIqEWiMD{Qr@iRbAiTdA_RtA{T`B_RlCwMvC_L~Loc@zKkb@vSoq@fMmPzScUby@u`AbNgN`FaGnFqJfFsKjBiDlBqCnDqC~DkBtGIvBD|ObEzWdM|WhNfMbCxIdAjFj@lKd@xOp@~I]tGI|GeAfNoBn]kGvTcExFaDzEwFnFqIrGkPpEcLxFqRfEcQnGyb@`Ikh@pKag@hBeQ`AgPbA}GnBwGlC_GdBuGxAsJZwC??ZwC`@gFbAqK|Pqp@dUs`Btv@e{CjTimB|d@w|C|@iLJmJsBk{@S{[??IgKlNzToMfRrBj{@KlJ}@hL}d@v|CkThmBuv@d{CeUr`B}Ppp@cApKa@fFWdC??_@hDyArJeBtGjXhHjKtB`]lHzIZbHCbIQzETtFtAbHrFx[lVrDxItCjJrDbKpDtFhEvFbG~DdFtCn\\rMrk@xRrTnGnNbHdMbFdOxIpQnL|LtHjEnG~IrNjKrUvLt]tGpLxIxOlNrMjNrPbTpVbWn^~MjUhM`TlKpQnEhKxC|LhFtXzCjOfAxF`ExPlGlO|G`PbFtQlDjQhCdP`FhRjErLvFhKxMtRzHrL|HzN|ErP`ChQbEhO|GxL`L~ObMnRrH~P~GtRnEfSxH`ZvDfK|@bC??zAbEtHbN~EtNrIzV`Rha@rEfNJzHo@bQoBfWyGfZmE`VqC|TmBrZs@tYGb]BzYpAnXzAdTjCdMfG`PnFlOnGjXzIla@pHre@|I`h@xHfd@tGh\\xJnZr_@tiAvE~PfFhUbApTj@d\\n@nc@nBhx@jBne@dE~`A`Czc@jDdXdGv[|G`e@xH`}@bAz\\zBvXpApT|@|QV`Vo@xY{Abo@y@ta@`@pQvCrOnDtKlCbGtF~IjD~FhCnHxBvKjFxTxF~\\bDxTvCrS|B|NlFxIdFzJ|CnSdEvStF`LhKpLfHnH|EzKvJ~RjGpObD`QdEjP|HhSvJbKdOrKxh@r^bWvTfPhO`J|IjExHdI`Q`HdL|DlG`PbE`HfAvNY`Q{BbPqAd[_Ddd@yDrK}AzNNrL`BbXvExKtD|CbEvHzPtJxRfFhNzCrH`G~HtH|JtBnC|Sl]vHtQpIvWvJ`a@pG`d@xLxu@tDhWnFtQrJfYpJ~[xElY`B|JfCjGdGlJ|GfKrFbE|F{BzGuBlMmA~KtEvJzHlFvExGlKfCfMvCrQhCxKhG`PfF`Jpl@bQfgAaOvrAzi@lKrIrdAbz@`V|EpWh`@phClZ|Ky[dI{QhG_LfFaElJiF|MoCjHkBvEuDjDeJjIc\\fH}XbCgIhBoDzJeJvNuGrQoEhToDxNaFvHsHjRaUxF{EjKKtZbDtN|AbIvArGbD~EfFjFpLnCnGbQzTpInKtD~G~B`NxIfe@~E`\\nB~LjB`HvEjE~LrGlCqCtKyBnJWvHo@rHoCdGkGrF_IdGiI~G}D|OqFzWkHlWuG`IOnUfAdO|@dUm@~LCnPf@nKlA`JdBdGh@rFRxHaA~TsE??vJqB|JyBbLwBrL]lQm@dYiAxJq@jIwBxJwDr[oNvG}DnHmE`HkH~EuHjG_MxH}XrPwz@zI_f@~G{`@vCcPdByGhHcNfJmNvH}KlJwJfLuLnGgKnI_NvUwh@tHaUlBiJtAeK`@uR[oWmAuZMeMXyMdA}GzFuPfJ}PbQoTzKmJ`OyIho@yw@rPuShVce@bPk]jIyUtPub@jGiQl\\cv@rIqNlPqPtQkM|R}Wr^yo@v`@{~@`QaZhEaEnDuCdyBirCpt@a_AdTgTdGeGdP}N~RoQ`jBmyA~XgQ`SoItWmIjVyEjV{Clk@qCxNLhSB~y@_GbNu@jDs@dCw@`DyBtDsGzHwb@t@uEpBwKlBkMzFue@p@_A","direction":["outbound","outbound","outbound","outbound","outbound","outbound","outbound","outbound","outbound"]},{"routeId":"RT2","routeLinkIds":["RL10","RL11","RL12","RL13","RL14","RL15","RL16","RL17","RL18","RL19"],"description":"Wenallt - Talbot Hotel","stopPoints":["5230WDB47548","5230CGX16406","5230CGX16423","5230AWD71036","5230AWD71034","5230CGX16407","5230CGX16417","5230CGX16484","5230WDB47545","5230WDB46530","5230AWD71030"],"distance":[1656,29,3201,2462,837,888,1830,6301,3529,673],"tracks":"u~zxbBljzoFnKiOf[ea@bb@en@dLmY~ZslC`BiNzU_bBjOqgCxGsp@@eqCv@wQtOosAunAcPefDk_AqMkCqjAnTqItEiFxDn@pEUpEc@tC??yA|JdBqLVaBTqEo@qEhFyDpIuEpjAoTpMjCdfDj_AtnAbP~Dkk@`V{mA`Jsp@eKs|@cAyIaAy[hDcQzUmZxSrVzTpSlyAlh@dItCzENfm@{Ddx@{`@vPgO~Qm]rLaHhFqAlj@hAbRcCnF}ClT_U~Q_j@xCsSsBy^DiIjBsHbJ{R`^_h@bNqMro@mNrg@dBpHmAnl@ef@ri@_]je@_j@he@geAxP_ZdSkWbUyRxl@eXjIwDjf@a[do@aSvb@mE|q@fC~AP??dKfArT`CxVaIhg@}l@dReKhl@qAtl@rBpI}At\\aTlc@_f@fQoN~YeOrd@_Mps@oXjTeKrEcEpFcInCoHxBgJpBaLhAcRpAkRp@mRIqEWiMD{Qr@iRbAiTdA_RtA{T`B_RlCwMvC_L~Loc@zKkb@vSoq@fMmPzScUby@u`AbNgN`FaGnFqJfFsKjBiDlBqCnDqC~DkBtGIvBD|ObEzWdM|WhNfMbCxIdAjFj@lKd@xOp@~I]tGI|GeAfNoBn]kGvTcExFaDzEwFnFqIrGkPpEcLxFqRfEcQnGyb@`Ikh@pKag@hBeQ`AgPbA}GnBwGlC_GdBuGxAsJZwC??ZwC`@gFbAqK|Pqp@dUs`Btv@e{CjTimB|d@w|C|@iLJmJsBk{@S{[??IgKlNzToMfRrBj{@KlJ}@hL}d@v|CkThmBuv@d{CeUr`B}Ppp@cApKa@fFWdC??_@hDyArJeBtGjXhHjKtB`]lHzIZbHCbIQzETtFtAbHrFx[lVrDxItCjJrDbKpDtFhEvFbG~DdFtCn\\rMrk@xRrTnGnNbHdMbFdOxIpQnL|LtHjEnG~IrNjKrUvLt]tGpLxIxOlNrMjNrPbTpVbWn^~MjUhM`TlKpQnEhKxC|LhFtXzCjOfAxF`ExPlGlO|G`PbFtQlDjQhCdP`FhRjErLvFhKxMtRzHrL|HzN|ErP`ChQbEhO|GxL`L~ObMnRrH~P~GtRnEfSxH`ZvDfK|@bC??zAbEtHbN~EtNrIzV`Rha@rEfNJzHo@bQoBfWyGfZmE`VqC|TmBrZs@tYGb]BzYpAnXzAdTjCdMfG`PnFlOnGjXzIla@pHre@|I`h@xHfd@tGh\\xJnZr_@tiAvE~PfFhUbApTj@d\\n@nc@nBhx@jBne@dE~`A`Czc@jDdXdGv[|G`e@xH`}@bAz\\zBvXpApT|@|QV`Vo@xY{Abo@y@ta@`@pQvCrOnDtKlCbGtF~IjD~FhCnHxBvKjFxTxF~\\bDxTvCrS|B|NlFxIdFzJ|CnSdEvStF`LhKpLfHnH|EzKvJ~RjGpObD`QdEjP|HhSvJbKdOrKxh@r^bWvTfPhO`J|IjExHdI`Q`HdL|DlG`PbE`HfAvNY`Q{BbPqAd[_Ddd@yDrK}AzNNrL`BbXvExKtD|CbEvHzPtJxRfFhNzCrH`G~HtH|JtBnC|Sl]vHtQpIvWvJ`a@pG`d@xLxu@tDhWnFtQrJfYpJ~[xElY`B|JfCjGdGlJ|GfKrFbE|F{BzGuBlMmA~KtEvJzHlFvExGlKfCfMvCrQhCxKhG`PfF`Jpl@bQfgAaOvrAzi@lKrIrdAbz@`V|EpWh`@phClZ|Ky[dI{QhG_LfFaElJiF|MoCjHkBvEuDjDeJjIc\\fH}XbCgIhBoDzJeJvNuGrQoEhToDxNaFvHsHjRaUxF{EjKKtZbDtN|AbIvArGbD~EfFjFpLnCnGbQzTpInKtD~G~B`NxIfe@~E`\\nB~LjB`HvEjE~LrGlCqCtKyBnJWvHo@rHoCdGkGrF_IdGiI~G}D|OqFzWkHlWuG`IOnUfAdO|@dUm@~LCnPf@nKlA`JdBdGh@rFRxHaA~TsE??vJqB|JyBbLwBrL]lQm@dYiAxJq@jIwBxJwDr[oNvG}DnHmE`HkH~EuHjG_MxH}XrPwz@zI_f@~G{`@vCcPdByGhHcNfJmNvH}KlJwJfLuLnGgKnI_NvUwh@tHaUlBiJtAeK`@uR[oWmAuZMeMXyMdA}GzFuPfJ}PbQoTzKmJ`OyIho@yw@rPuShVce@bPk]jIyUtPub@jGiQl\\cv@rIqNlPqPtQkM|R}Wr^yo@v`@{~@`QaZhEaEnDuCdyBirCpt@a_AdTgTdGeGdP}N~RoQ`jBmyA~XgQ`SoItWmIjVyEjV{Clk@qCxNLhSB~y@_GbNu@jDs@dCw@hDtVjLlQpXjMfO`M`XfYjNl[rFnJ_GdRgB|S??sGnv@{@xXvFzSsH|M?lA_@kAD@@ArA{b@z@yXzJmkA~FeRsFoJkNm[wKce@_Is^_DyM{I}RoIoPyN_Vt@uEpBwKlBkMzFue@p@_A","direction":["outbound","outbound","outbound","outbound","outbound","outbound","outbound","outbound","outbound","outbound"]},{"routeId":"RT3","routeLinkIds":["RL20","RL21","RL22","RL23","RL24","RL25","RL26","RL27","RL28","RL29","RL30","RL31","RL32","RL33","RL34","RL35"],"description":"Aberystwyth Bus Station Stand 5 - Wellington House","stopPoints":["5230WDB25330","5230CGX16447","5230CGX16359","5230AWD71055","5230AWD71057","5230AWD71058","5230CGX16402","5230AWD71048","5230CGX16416","5230CGX16405","5230WDB47548","5230CGX16406","5230CGX16423","5230AWD71036","5230AWD71034","5230CGX16407","5230CGX16408"],"distance":[401,325,362,441,254,6019,1425,3390,827,1548,1656,29,3201,2462,837,2207],"tracks":"s_c~bBzsaxFnAtD{D~PhAxDhAnEjAlElA|Dv@tCfD`LrHvTnUxo@j@i@`@Mp@Bh@Zd@t@VfADj@EnBnD~@lEnAfQhM`JzFzHfGnRnQdK~TfB|D~EzL??`C`GdCxMzAg@rDm@jn@uDxEHjF|@nDv@fMdCfMhDtC^vCPfEWvI}@rOyBtASdIiArCkA??fDuAzFkEjG}IlD_NbBsMf@kVAms@fBiWxC}WhGg\\jDgMlBgHnEgMjFgKbQoV??bE_Gle@un@zi@sm@l{@i{@xn@{h@tL_K??`KoInCyCpToUzR_Vnd@qm@`S}[??tWub@`NiVpHiLhBeCxFwI|BgDnc@yp@bKoO|Va^vEiLhFeVzBs]e@][q@QoA@cAN}@Zo@b@_@VGf@Dd@X\\l@P|@@~AnKMnFe@nAKnKyJf^gj@bIcJtHkMvJoI`G_EnL~PhwBpCdGkExq@ubCAH~SkoA`R{g@bb@sjArj@uzB~i@oaChe@kgAzl@ssA~u@kcBnLq\\pAy@We@hQk_@rgAepBlMiW~dCu`Fdo@ilAfUyg@jPoj@fEeLfCaHpi@gyAbCwPnGgRzc@goAvIwQh@kIxJk\\`EyP~a@unCnAsyApBsk@zGqfAjEaiA~BsWnNi~AtHel@bCon@wAe}EdBugAjGmj@vOs~@tO{d@rRua@nSa[xU}TtJqEjSaDnHaF`I}MtDoGl]{wA~UaeBdi@ouCfGik@xHmjBpIw{@|CqRtCeQdJcYpAaEpHqLri@wk@jRw[vt@iiBl^mrA~Qan@??bByF`QiXpMqO~GgFdGmCdQeG|OuFbe@gSrJkAfO@pb@\\fR{AdTwF~n@mV`ZNtb@xQ~_@jIhJeGba@ej@~Zcc@le@{a@hLuJvg@_uAxWoe@h`@m]~w@wm@pi@ab@hCqB??lCsBEOzs@_v@tUe_@lx@__B|GmLp\\qa@zh@}o@thAkbBdGaJpp@{u@`Vo]nSc`@fe@odB|f@gzCtRo`Ax[gsA~EeZlNkz@vWolB|NgpB~VmkCjw@a_FxMocAhl@smDtW{dCdg@mgDx]ugAb[}m@z_@yf@vzAenBnNmK~KyJp^{Y?AhFwD??nA}@|XwShImGhl@}c@jc@a`@rSsOdIuEpM?zoA`Xbf@xKp`@zEjc@sC~R{ClNeFlH}BjQsNfPoT??rBoC`EkGxGgKzFiNnIoYrAyE~Tcw@fYo`@hJoLzTaY|H}OzG}RrFoS~CkVv\\emDbAeIbA}ErBuDfAy@jCoBlJoDf[iU~FgFpI_HhJ}Etc@uUpr@_e@bz@s\\|`@oLrIuErMeXfUJzYn@tQp@pY}ErZCfSsH~GoGfIkLnWa_@??nKiOf[ea@bb@en@dLmY~ZslC`BiNzU_bBjOqgCxGsp@@eqCv@wQtOosAunAcPefDk_AqMkCqjAnTqItEiFxDn@pEUpEc@tC??yA|JdBqLVaBTqEo@qEhFyDpIuEpjAoTpMjCdfDj_AtnAbP~Dkk@`V{mA`Jsp@eKs|@cAyIaAy[hDcQzUmZxSrVzTpSlyAlh@dItCzENfm@{Ddx@{`@vPgO~Qm]rLaHhFqAlj@hAbRcCnF}ClT_U~Q_j@xCsSsBy^DiIjBsHbJ{R`^_h@bNqMro@mNrg@dBpHmAnl@ef@ri@_]je@_j@he@geAxP_ZdSkWbUyRxl@eXjIwDjf@a[do@aSvb@mE|q@fC~AP??dKfArT`CxVaIhg@}l@dReKhl@qAtl@rBpI}At\\aTlc@_f@fQoN~YeOrd@_Mps@oXjTeKrEcEpFcInCoHxBgJpBaLhAcRpAkRp@mRIqEWiMD{Qr@iRbAiTdA_RtA{T`B_RlCwMvC_L~Loc@zKkb@vSoq@fMmPzScUby@u`AbNgN`FaGnFqJfFsKjBiDlBqCnDqC~DkBtGIvBD|ObEzWdM|WhNfMbCxIdAjFj@lKd@xOp@~I]tGI|GeAfNoBn]kGvTcExFaDzEwFnFqIrGkPpEcLxFqRfEcQnGyb@`Ikh@pKag@hBeQ`AgPbA}GnBwGlC_GdBuGxAsJZwC??ZwC`@gFbAqK|Pqp@dUs`Btv@e{CjTimB|d@w|C|@iLJmJsBk{@S{[??IgKmEuqB{D}_Ac@wkAoBkLuFcWqEkYiGua@}Gcc@iGsc@wG}]wHwZaFoKiEcJ_FqOyC_Ys@oMMiQ`B_\\jBwPvEqPbiBmhGf|@efCjR_u@n~AqsIvD__@tDsbA[qjAp@oL`Mop@tNa^xKwM`FoCnHeCfW}@nJq@","direction":["outbound","outbound","outbound","outbound","outbound","outbound","outbound","outbound","outbound","outbound","outbound","outbound","outbound","outbound","outbound","outbound"]},{"routeId":"RT4","routeLinkIds":["RL36","RL37","RL38","RL39","RL40","RL41","RL42","RL43","RL44","RL45","RL46","RL47","RL48","RL49","RL50","RL51","RL52","RL53","RL54","RL55"],"description":"Aberystwyth Bus Station Stand 5 - Talbot Hotel","stopPoints":["5230WDB25330","5230CGX16447","5230CGX16359","5230AWD71055","5230AWD71057","5230AWD71058","5230CGX16402","5230AWD71048","5230CGX16416","5230CGX16405","5230WDB47548","5230CGX16406","5230CGX16423","5230WDB23420","5230AWD71040","5230CGX16612","5230AWD71038","5230AWD71037","5230CGX16408","5230CGX16409","5230AWD71030"],"distance":[401,325,362,441,254,6019,1425,3390,827,1548,1656,29,1154,3911,2155,1460,3808,1699,374,8892],"tracks":"s_c~bBzsaxFnAtD{D~PhAxDhAnEjAlElA|Dv@tCfD`LrHvTnUxo@j@i@`@Mp@Bh@Zd@t@VfADj@EnBnD~@lEnAfQhM`JzFzHfGnRnQdK~TfB|D~EzL??`C`GdCxMzAg@rDm@jn@uDxEHjF|@nDv@fMdCfMhDtC^vCPfEWvI}@rOyBtASdIiArCkA??fDuAzFkEjG}IlD_NbBsMf@kVAms@fBiWxC}WhGg\\jDgMlBgHnEgMjFgKbQoV??bE_Gle@un@zi@sm@l{@i{@xn@{h@tL_K??`KoInCyCpToUzR_Vnd@qm@`S}[??tWub@`NiVpHiLhBeCxFwI|BgDnc@yp@bKoO|Va^vEiLhFeVzBs]e@][q@QoA@cAN}@Zo@b@_@VGf@Dd@X\\l@P|@@~AnKMnFe@nAKnKyJf^gj@bIcJtHkMvJoI`G_EnL~PhwBpCdGkExq@ubCAH~SkoA`R{g@bb@sjArj@uzB~i@oaChe@kgAzl@ssA~u@kcBnLq\\pAy@We@hQk_@rgAepBlMiW~dCu`Fdo@ilAfUyg@jPoj@fEeLfCaHpi@gyAbCwPnGgRzc@goAvIwQh@kIxJk\\`EyP~a@unCnAsyApBsk@zGqfAjEaiA~BsWnNi~AtHel@bCon@wAe}EdBugAjGmj@vOs~@tO{d@rRua@nSa[xU}TtJqEjSaDnHaF`I}MtDoGl]{wA~UaeBdi@ouCfGik@xHmjBpIw{@|CqRtCeQdJcYpAaEpHqLri@wk@jRw[vt@iiBl^mrA~Qan@??bByF`QiXpMqO~GgFdGmCdQeG|OuFbe@gSrJkAfO@pb@\\fR{AdTwF~n@mV`ZNtb@xQ~_@jIhJeGba@ej@~Zcc@le@{a@hLuJvg@_uAxWoe@h`@m]~w@wm@pi@ab@hCqB??lCsBEOzs@_v@tUe_@lx@__B|GmLp\\qa@zh@}o@thAkbBdGaJpp@{u@`Vo]nSc`@fe@odB|f@gzCtRo`Ax[gsA~EeZlNkz@vWolB|NgpB~VmkCjw@a_FxMocAhl@smDtW{dCdg@mgDx]ugAb[}m@z_@yf@vzAenBnNmK~KyJp^{Y?AhFwD??nA}@|XwShImGhl@}c@jc@a`@rSsOdIuEpM?zoA`Xbf@xKp`@zEjc@sC~R{ClNeFlH}BjQsNfPoT??rBoC`EkGxGgKzFiNnIoYrAyE~Tcw@fYo`@hJoLzTaY|H}OzG}RrFoS~CkVv\\emDbAeIbA}ErBuDfAy@jCoBlJoDf[iU~FgFpI_HhJ}Etc@uUpr@_e@bz@s\\|`@oLrIuErMeXfUJzYn@tQp@pY}ErZCfSsH~GoGfIkLnWa_@??nKiOf[ea@bb@en@dLmY~ZslC`BiNzU_bBjOqgCxGsp@@eqCv@wQtOosAunAcPefDk_AqMkCqjAnTqItEiFxDn@pEUpEc@tC??yA|JdBqLVaBTqEo@qEkB}E_CuBuDw@}@CwBGsCNoACcBy@kBuA}BeDkAgDu@qDqDaUmEuOqJo[cGaSgi@ud@_g@i{@ssAmmAkTyE}j@ct@cJ{XgHi[_Eo^{d@qjBmQibAeLen@sBeL@?mKqk@??k@_DiCmh@cCq~@cDaYmAiSy@ko@qD}u@yEubAoCyq@qHih@kBmQqEuq@mGugAsFet@iFu`@iAio@qCeu@{A{q@eDa_@v@wQpL_}AdBsz@h@ar@yRgaAiCiGqKmbAAoc@gE_gAoE_j@}Fih@uAgd@f@{r@|Iw_@~LwbAnL{aAxAspAsCghB@g]|Acg@pGar@?il@mOkt@i]}YyV_NyC}DgN}e@{Hsb@sQwsAeJ{TgCuNFwO~Dkd@kJc|@{Byt@mBkR{IcYoWgb@kGcYU_ToBaIuBoGiNqRuZekAeD{R_D_i@oGw]eE}cAyAuIoMu\\kGu_@wCeHyg@ch@lW_}@hT{_AvRgqA|Co]jBek@pCoP??jAyGta@caAvg@_j@dOo`@bEkY~Jaw@xLad@jLcRvMuSnf@kj@hNaNlRcRhKoP`BwIlAoY}GmkAoEa_@kE_^yEe`CVwb@nMcZrH}]n\\}i@n^_RtRmV`Ki[vCiSn@}PoR{i@gJaPsEqDaIa`@}@k`@YaNkFg^Dq[dBcVfEeLrEnAnJnDhCjInDnv@nDvYzHfWrMdXvYvKl[hIpZpFtb@dD`m@`I??bGx@h[bMfR~LtGnCrElCjFOrDyC|CeGrAyTbAqKjCeIpDcAlEbDdDjI`MrZzVpVlT`XhWbh@jLxVtI|o@hO~a@vjBncBdNrUbH~XgBxMqAzMbA|UvHlf@~J~l@pPzc@zTjd@zQ~PjUbZtNhQhLjPvJ|L~[_MnNuCxGDdLm@jAK??tIy@tRcNxd@{Mfg@cLf^yV~P_JpQmHfNcBnKkIfIaSrIoUvIqO`J{Frb@}Df]]lKwChKcFvUyGpj@{Bne@hBtHd@l]vBtWQ`VwJxMfElVvKpR|FtTdAvVaAjo@}Ixi@uQxYcQbVgSnm@gm@~Mc[tHmb@x@{m@ZmPt@wKxE}U|CmK~FiIbRaIpR}H~QeNrTgO|U_Lnh@gZvQqMjMiRjl@u_Ar]{i@pPgVlYaSdQqFn\\NtVtEtYjShr@ji@~]xNlk@rIta@u@rk@sLlS{Jz_Aep@xYkS|DoCf^yW`d@eVteBwq@pQl@rUpVjZlXvLvPdJjUzGfTtGxSbEzR~B`L??zCpN``@jtAbs@ruBpRd`Al^n`BpMxf@jOre@xMx[zLj]~MhV`x@`~@jR`SxTtRhQzLxGzB|GRjGc@hRkNbRaQtYsO`ZuLnQ{DvVPbhArMp`@tJ~UbRxHdFhJhMv]pe@vDnHtCtIfW}@nJq@??lGe@~NuDdKuFpUiPjLcAlK\\rIfB~FhCdMpMpSvVxNjIp`@hV~Aj@rBD??hTXtj@fMpQtKdZzZ`t@jj@b_@~_@lh@jp@z_@n`@tVbW|HhGbwAjhAhh@ro@vc@hYvaAfhAli@tr@bV`Qt]`TlQvM~NnZ`Jb]|Y~cC`CfVbK`dAvDdW~Nx[fi@zg@xo@zc@~p@bu@zb@fv@tt@tiBbN~\\|z@|gBp[~{@jd@|nAld@puAhb@reAx]|kAlc@`kC~KpZz^zp@nZpd@ltAzlA~[t^`PvX~b@`iA~C`Nzf@`{D~Jvc@|U`q@l[dj@zTnTdaAbs@xG|GjNzWxOfa@`Orq@lRfr@js@vtBl{@t}Bjs@bsArc@nn@n\\|_@lW|[~Q~Pbi@f]rTlHpVvCh^|AvTvOvk@ff@lRhKlHdG`IzN`H`V`O`l@`L`T|K`XxJlWfbAl{@fy@je@zd@bj@pYvc@~G|M`dA~oBtr@vy@j|@dlA`b@f[b~@peAxg@hh@toAv|@jr@d{@`UtRdc@rNld@pHtzA_Bdq@vKdX`Bh\\wCr_@iDhWt@`fFb`AhEKlfArDla@fAxR|Bva@dKnOlG~MjFlN~K|JlKhL`UfMz`@t@uEpBwKlBkMzFue@p@_A","direction":["outbound","outbound","outbound","outbound","outbound","outbound","outbound","outbound","outbound","outbound","outbound","outbound","outbound","outbound","outbound","outbound","outbound","outbound","outbound","outbound"]},{"routeId":"RT5","routeLinkIds":["RL56","RL57","RL58","RL59","RL60","RL61","RL62","RL63","RL64","RL65","RL66","RL67","RL68","RL69","RL70","RL71","RL72","RL73","RL74","RL75","RL76"],"description":"Aberystwyth Bus Station Stand 5 - Talbot Hotel","stopPoints":["5230WDB25330","5230CGX16447","5230CGX16359","5230AWD71055","5230AWD71057","5230AWD71058","5230CGX16402","5230AWD71048","5230AWD71049","5230CGX16403","5230CGX16404","5230CGX16416","5230CGX16405","5230WDB47548","5230CGX16406","5230CGX16423","5230AWD71036","5230AWD71034","5230CGX16407","5230CGX16408","5230CGX16409","5230AWD71030"],"distance":[401,325,362,441,254,6019,1425,2810,1743,723,1717,827,1548,1656,29,3201,2462,837,2207,374,8892],"tracks":"s_c~bBzsaxFnAtD{D~PhAxDhAnEjAlElA|Dv@tCfD`LrHvTnUxo@j@i@`@Mp@Bh@Zd@t@VfADj@EnBnD~@lEnAfQhM`JzFzHfGnRnQdK~TfB|D~EzL??`C`GdCxMzAg@rDm@jn@uDxEHjF|@nDv@fMdCfMhDtC^vCPfEWvI}@rOyBtASdIiArCkA??fDuAzFkEjG}IlD_NbBsMf@kVAms@fBiWxC}WhGg\\jDgMlBgHnEgMjFgKbQoV??bE_Gle@un@zi@sm@l{@i{@xn@{h@tL_K??`KoInCyCpToUzR_Vnd@qm@`S}[??tWub@`NiVpHiLhBeCxFwI|BgDnc@yp@bKoO|Va^vEiLhFeVzBs]e@][q@QoA@cAN}@Zo@b@_@VGf@Dd@X\\l@P|@@~AnKMnFe@nAKnKyJf^gj@bIcJtHkMvJoI`G_EnL~PhwBpCdGkExq@ubCAH~SkoA`R{g@bb@sjArj@uzB~i@oaChe@kgAzl@ssA~u@kcBnLq\\pAy@We@hQk_@rgAepBlMiW~dCu`Fdo@ilAfUyg@jPoj@fEeLfCaHpi@gyAbCwPnGgRzc@goAvIwQh@kIxJk\\`EyP~a@unCnAsyApBsk@zGqfAjEaiA~BsWnNi~AtHel@bCon@wAe}EdBugAjGmj@vOs~@tO{d@rRua@nSa[xU}TtJqEjSaDnHaF`I}MtDoGl]{wA~UaeBdi@ouCfGik@xHmjBpIw{@|CqRtCeQdJcYpAaEpHqLri@wk@jRw[vt@iiBl^mrA~Qan@??bByF`QiXpMqO~GgFdGmCdQeG|OuFbe@gSrJkAfO@pb@\\fR{AdTwF~n@mV`ZNtb@xQ~_@jIhJeGba@ej@~Zcc@le@{a@hLuJvg@_uAxWoe@h`@m]~w@wm@pi@ab@hCqB??lCsBEO_FhFhAqMhDwn@vMypBMqXwHqtBcSej@w[kh@{H_\\kG}Oov@atA{IcWaUib@me@yhAcCoL]og@kAyIq`@a~AgEc^TyYaFss@oDkqAeCyxB|Cg`@w@sd@tKwbDhDm{@eNgx@oHei@cHwo@mMcjAwM}yAeBgs@pBa~@lDiZ[qKqAqPoLyf@{L}{@~VoeErPkcAxPmx@~BgD??rBwCtFuG`D_ErI_Eg@ek@zBcIjHcJ~CaJ`AmGrHwe@LmMaJ{oAjBiSzMuSdB}I@yWfCgm@iBu{@D}qAvFip@|E_CfNgIhDqBzh@sJhl@eTnd@}g@|Og\\ls@ux@nm@wU`_@mq@d^qg@jK{JpOwb@xT}YvFcBrXfMfD_@nCsD~Dg]`D_En]ePfJ}J|HaPrBuA`HsE??rIwFdWeMfWeEfUuKtScXrFaOrZutArYiw@tV{nBtFmYf]_w@|Vy^zCsEBtI??@rApA~[tMjxAhy@`sGf_Bx{HCJg@c@LTdSv|@jRf~@zL~\\dg@rtA~m@~wA`V~m@vZ~z@ti@d`Bbn@~fBhFwD??nA}@|XwShImGhl@}c@jc@a`@rSsOdIuEpM?zoA`Xbf@xKp`@zEjc@sC~R{ClNeFlH}BjQsNfPoT??rBoC`EkGxGgKzFiNnIoYrAyE~Tcw@fYo`@hJoLzTaY|H}OzG}RrFoS~CkVv\\emDbAeIbA}ErBuDfAy@jCoBlJoDf[iU~FgFpI_HhJ}Etc@uUpr@_e@bz@s\\|`@oLrIuErMeXfUJzYn@tQp@pY}ErZCfSsH~GoGfIkLnWa_@??nKiOf[ea@bb@en@dLmY~ZslC`BiNzU_bBjOqgCxGsp@@eqCv@wQtOosAunAcPefDk_AqMkCqjAnTqItEiFxDn@pEUpEc@tC??yA|JdBqLVaBTqEo@qEhFyDpIuEpjAoTpMjCdfDj_AtnAbP~Dkk@`V{mA`Jsp@eKs|@cAyIaAy[hDcQzUmZxSrVzTpSlyAlh@dItCzENfm@{Ddx@{`@vPgO~Qm]rLaHhFqAlj@hAbRcCnF}ClT_U~Q_j@xCsSsBy^DiIjBsHbJ{R`^_h@bNqMro@mNrg@dBpHmAnl@ef@ri@_]je@_j@he@geAxP_ZdSkWbUyRxl@eXjIwDjf@a[do@aSvb@mE|q@fC~AP??dKfArT`CxVaIhg@}l@dReKhl@qAtl@rBpI}At\\aTlc@_f@fQoN~YeOrd@_Mps@oXjTeKrEcEpFcInCoHxBgJpBaLhAcRpAkRp@mRIqEWiMD{Qr@iRbAiTdA_RtA{T`B_RlCwMvC_L~Loc@zKkb@vSoq@fMmPzScUby@u`AbNgN`FaGnFqJfFsKjBiDlBqCnDqC~DkBtGIvBD|ObEzWdM|WhNfMbCxIdAjFj@lKd@xOp@~I]tGI|GeAfNoBn]kGvTcExFaDzEwFnFqIrGkPpEcLxFqRfEcQnGyb@`Ikh@pKag@hBeQ`AgPbA}GnBwGlC_GdBuGxAsJZwC??ZwC`@gFbAqK|Pqp@dUs`Btv@e{CjTimB|d@w|C|@iLJmJsBk{@S{[??IgKmEuqB{D}_Ac@wkAoBkLuFcWqEkYiGua@}Gcc@iGsc@wG}]wHwZaFoKiEcJ_FqOyC_Ys@oMMiQ`B_\\jBwPvEqPbiBmhGf|@efCjR_u@n~AqsIvD__@tDsbA[qjAp@oL`Mop@tNa^xKwM`FoCnHeCfW}@nJq@??lGe@~NuDdKuFpUiPjLcAlK\\rIfB~FhCdMpMpSvVxNjIp`@hV~Aj@rBD??hTXtj@fMpQtKdZzZ`t@jj@b_@~_@lh@jp@z_@n`@tVbW|HhGbwAjhAhh@ro@vc@hYvaAfhAli@tr@bV`Qt]`TlQvM~NnZ`Jb]|Y~cC`CfVbK`dAvDdW~Nx[fi@zg@xo@zc@~p@bu@zb@fv@tt@tiBbN~\\|z@|gBp[~{@jd@|nAld@puAhb@reAx]|kAlc@`kC~KpZz^zp@nZpd@ltAzlA~[t^`PvX~b@`iA~C`Nzf@`{D~Jvc@|U`q@l[dj@zTnTdaAbs@xG|GjNzWxOfa@`Orq@lRfr@js@vtBl{@t}Bjs@bsArc@nn@n\\|_@lW|[~Q~Pbi@f]rTlHpVvCh^|AvTvOvk@ff@lRhKlHdG`IzN`H`V`O`l@`L`T|K`XxJlWfbAl{@fy@je@zd@bj@pYvc@~G|M`dA~oBtr@vy@j|@dlA`b@f[b~@peAxg@hh@toAv|@jr@d{@`UtRdc@rNld@pHtzA_Bdq@vKdX`Bh\\wCr_@iDhWt@`fFb`AhEKlfArDla@fAxR|Bva@dKnOlG~MjFlN~K|JlKhL`UfMz`@t@uEpBwKlBkMzFue@p@_A","direction":["outbound","outbound","outbound","outbound","outbound","outbound","outbound","outbound","outbound","outbound","outbound","outbound","outbound","outbound","outbound","outbound","outbound","outbound","outbound","outbound","outbound"]},{"routeId":"RT6","routeLinkIds":["RL77","RL78","RL79","RL80","RL81","RL82","RL83","RL84","RL85","RL86","RL87","RL88","RL89","RL90","RL91","RL92","RL93","RL94","RL95"],"description":"Pontrhydfendigaid - Aberystwyth Bus Station Stand 5","stopPoints":["5230AWD71032","5230AWD71033","5230CGX16417","5230WDB23421","5230CGX16406","5230CGX16423","5230WDB47547","5230AWD71044","5230AWD71047","5230CGX16415","5230AWD71050","5230AWD71051","5230AWD71053","5230AWD71054","5230WDB23416","5230AWD71056","5230WDB48336","5230WDB22901","5230AWD71097","5230WDB25330"],"distance":[2213,832,2463,3202,29,1508,1699,817,3403,1418,5508,391,261,546,358,566,215,148,322],"tracks":"wmdvbBfewjFwJr@gW|@oHdCaFnCyKvMuN`^aMnp@q@nLZpjAuDrbAwD~^o~ApsIkR~t@g|@dfCciBlhGwEpPkBvPaB~[LhQr@nMxC~X~EpOhEbJ`FnKvHvZvG|]hGrc@|Gbc@hGta@pEjYtFbWnBjLb@vkAzD|_AlEtqBJzO??PfWrBj{@KlJ}@hL}d@v|CkThmBuv@d{CeUr`B}Ppp@cApKa@fFWdC??_@hDyArJeBtGmC~FoBvGcA|GaAfPiBdQqK`g@aIjh@oGxb@gEbQyFpRqEbLsGjPoFpI{EvFyF`DwTbEo]jGgNnB}GdAuGH_J\\yOq@mKe@kFk@yIeAgMcC}WiN{WeM}OcEwBEuGH_EjBoDpCmBpCkBhDgFrKoFpJaF`GcNfNcy@t`A{SbUgMlPwSnq@{Kjb@_Mnc@wC~KmCvMaB~QuAzTeA~QcAhTs@hREzQVhMHpEq@lRqAjRiAbRqB`LyBfJoCnHqFbIsEbEkTdKqs@nXsd@~L_ZdOgQnNmc@~e@u\\`TqI|Aul@sBil@pAeRdKig@|l@yV`IsTaCmKiA??wAO}q@gCwb@lEeo@`Skf@`[kIvDyl@dXcUxReSjWyP~Yie@feAke@~i@si@~\\ol@df@qHlAsg@eBso@lNcNpMa^~g@cJzRkBrHEhIrBx^yCrS_R~i@mT~ToF|CcRbCmj@iAiFpAsL`H_Rl]wPfOex@z`@gm@zD{EOeIuCmyAmh@{TqSySsV{UlZiDbQ`Ax[bAxIdKr|@aJrp@aVzmA_Ejk@unAcPefDk_AqMkCqjAnTqItEiFxDn@pEUpEc@tC??yA|JdBqLVaBTqEo@qEhFyDpIuEpjAoTpMjCdfDj_AtnAbPuOnsAw@vQAdqCyGrp@kOpgC{U~aBaBhN_[rlCeLlYoJlN??sVv^g[da@_d@jo@gIjL_HnGgSrHsZBqY|EuQq@{Yo@gUKsMdXsItE}`@nLcz@r\\qr@~d@uc@tUiJ|EqI~G_GfFg[hUmJnDkCnBgAx@sBtDcA|EcAdIw\\dmD_DjVsFnS{G|R}H|O{T`YiJnLgYn`@_Ubw@sAxEoInY{FhNyGfKaEjG_EnF??{MnQkQrNmH|BmNdF_SzCkc@rCq`@{Ecf@yK{oAaXqM?eItEsSrOkc@``@il@|c@iIlG}XvSGB??qHpF?@q^zY_LxJoNlKwzAdnB{_@xf@c[|m@y]tgAeg@lgDuWzdCil@rmDyMncAkw@`_F_WlkC}NfpBwWnlBmNjz@_FdZy[fsAuRn`A}f@fzCge@ndBoSb`@aVn]qp@zu@eG`JuhAjbB{h@|o@q\\pa@}GlLmx@~~AuUd_@{s@~u@DNwGdFA@??oi@~a@_x@vm@i`@l]yWne@wg@~tAiLtJme@za@_[bc@ca@dj@iJdG_`@kIub@yQaZO_o@lVeTvFgRzAqb@]gOAsJjAce@fS}OtFeQdGeGlC_HfFqMpOaQhXwBjH??kQnl@m^lrAwt@hiBkRv[si@vk@qHpLqA`EeJbYuCdQ}CpRqIv{@yHljBgGhk@ei@nuC_V`eBm]zwAuDnGaI|MoH`FkS`DuJpEyU|ToS`[sRta@uOzd@wOr~@kGlj@eBtgAvAd}EcCnn@uHdl@oNh~A_CrWkE`iA{GpfAqBrk@oAryA_b@tnCaExPyJj\\i@jIwIvQ{c@foAoGfRcCvPqi@fyAgC`HgEdLkPnj@gUxg@eo@hlA_eCt`FmMhWsgAdpBiQj_@Vd@qAx@oLp\\_v@jcB{l@rsAie@jgA_j@naCsj@tzBcb@rjAaRzg@_TjoA@Iyq@tbCeGjEiwBqCoL_QaG~DwArKJrJaRRcIbJgSb[??_JbNoKxJoAJoFd@oKLO|@[n@c@^]Fg@G{Br]iFdVwEhL}V`^cKnOoc@xp@}BfDyFvIiBdCqApB??_FvHaNhVwk@r_Aod@pm@gGnH??sJnLqTnUoCxCwXnUyn@zh@m{@h{@{i@rm@me@tn@aEzF??eQrVkFfKoEfMmBfHkDfMiGf\\yC|WgBhW@ls@g@jVcBrMmD~MkG|I{FjEqAh@??iFvBeIhAuARsOxBwI|@gEVwCQuC_@gMiDgMeCoDw@kF}@yEIkn@tDsDl@{Af@sEbBeYzHgf@~Lw^nIkCK{VvL{@}EmC}J??eKu_@e]elA}DaNkAkA_B_FaJ__@??mC}KsFwWmTi|@iCaKaBeG??mG{UoCuOe@cD[aD_@qEzAw@`Ae@hDoAhNgCbCa@jMuLbOsMvSzt@rAfAlBj@r@{@z@[|@Dp@^n@|@`@tALhCEfA]~ArBlE~@hBdC|CN`@@D","direction":["inbound","inbound","inbound","inbound","inbound","inbound","inbound","inbound","inbound","inbound","inbound","inbound","inbound","inbound","inbound","inbound","inbound","inbound","inbound"]},{"routeId":"RT7","routeLinkIds":["RL96","RL97","RL98","RL99","RL100","RL101","RL102","RL103","RL104","RL105","RL106","RL107","RL108","RL109","RL110","RL111","RL112","RL113","RL114","RL115","RL116","RL117","RL118"],"description":"Tregaron, Square - Aberystwyth Bus Station Stand 5","stopPoints":["5230WDB23449","5230AWD71031","5230AWD71032","5230CGX16411","5230CGX16412","5230AWD71039","5230CGX16355","5230WDB23420","5230CGX16406","5230CGX16423","5230WDB47547","5230AWD71044","5230AWD71047","5230CGX16415","5230AWD71050","5230AWD71051","5230AWD71053","5230AWD71054","5230WDB23416","5230AWD71056","5230WDB48336","5230WDB22901","5230AWD71097","5230WDB25330"],"distance":[8937,373,1698,3811,1462,2155,3907,1156,29,1508,1699,817,3403,1418,5508,391,261,546,358,566,215,148,322],"tracks":"wjfrbB~g`oFrCdDStHG^{CcB}Cn@kBdC{Fte@mBjMqBvKu@tEgM{`@iLaU}JmKmN_L_NkFoOmGwa@eKyR}Bma@gAmfAsDiEJafFc`AiWu@s_@hDi\\vCeXaBeq@wKuzA~Amd@qHec@sNaUuRkr@e{@uoAw|@yg@ih@c~@qeAab@g[k|@elAur@wy@adA_pB_H}MqYwc@{d@cj@gy@ke@gbAm{@yJmW}KaXaLaTaOal@aHaVaI{NmHeGmRiKwk@gf@wTwOi^}AqVwCsTmHci@g]_R_QmW}[o\\}_@sc@on@ks@csAm{@u}Bks@wtBmRgr@aOsq@yOga@kN{WyG}GeaAcs@{ToTm[ej@}Uaq@_Kwc@{f@a{D_DaN_c@aiAaPwX_\\u^mtA{lAoZqd@{^{p@_LqZmc@akCy]}kAib@seAmd@quAkd@}nAq[_|@}z@}gBcN_]ut@uiB{b@gv@_q@cu@yo@{c@gi@{g@_Oy[wDeWcKadAaCgV}Y_dCaJc]_OoZmQwMu]aTcVaQmi@ur@waAghAwc@iYih@so@cwAkhA}HiGuVcW{_@o`@mh@kp@c_@_`@at@kj@eZ{ZqQuKuj@gMsTY??iBE_Bk@q`@iVyNkIqSwVeMqM_GiCsIgBmK]kLbAqUhPeKtF_OtDeGb@??wJr@gW|@uCuIwDoHw]qe@iJiMyHeF_VcRq`@uJchAsMwVQoQzDaZtLuYrOcR`QiRjNkGb@}GSyG{BiQ{LyTuRkRaSax@a~@_NiV{Lk]yMy[kOse@qMyf@m^o`BqRe`Acs@suBa`@ktAmCiM??mCiMcE{RuGyS{GgTeJkUwLwPkZmXsUqVqQm@ueBvq@ad@dVg^xW}DnCyYjS{_Adp@mSzJsk@rLua@t@mk@sI_^yNir@ki@uYkSuVuEo\\OeQpFmY`SqPfVs]zi@kl@t_AkMhRwQpMoh@fZ}U~KsTfO_RdNqR|HcR`I_GhI}ClKyE|Uu@vK[lPy@zm@uHlb@_Nb[om@fm@cVfSyYbQyi@tQko@|IwV`AuTeAqR}FmVwKyMgEaVvJuWPm]wBuHe@oe@iBqj@zBwUxGiKbFmKvCg]\\sb@|DaJzFwIpOsInUgI`SoKjIgNbBqQlH_Q~Ig^xVgg@bLyd@zMuRbNqJ|@??o@FeLl@yGEoNtC_\\~LwJ}LiLkPuNiQkUcZ{Q_Q{Tkd@qP{c@_K_m@wHmf@cA}UpA{MfByMcH_YeNsUwjBocBiO_b@uI}o@kLyViWch@mTaX{VqVaMsZeDkImEcDqDbAkCdIcApKsAxT}CdGsDxCkFNsEmCuGoCgR_Mi[cMeIgA??_k@sHub@eDqZqFm[iIwYwKsMeX{HgWoDwYoDov@iCkIoJoDsEoAgEdLeBbVEp[jFf^X`N|@j`@`I``@rEpDfJ`PnRzi@o@|PwChSaKh[uRlVo^~Qo\\|i@sH|]oMbZWvb@xEd`CjE~]nE`_@|GlkAmAnYaBvIiKnPmRbRiN`Nof@jj@wMtSkLbRyL`d@_K`w@cEjYeOn`@wg@~i@ua@baAgBjK??uB|LkBdk@}Cn]wRfqAiTz_AmW~|@xg@bh@vCdHjGt_@nMt\\xAtIdE|cAnGv]~C~h@dDzRtZdkAhNpRtBnGnB`IT~SjGbYnWfb@zIbYlBjRzBxt@jJb|@_Ejd@GvOfCtNdJzTrQvsAzHrb@fN|e@xC|DxV~Mh]|YlOjt@?hl@qG`r@}Abg@Af]rCfhByArpAoLzaA_MvbA}Iv_@g@zr@tAfd@|Fhh@nE~i@fE~fA@nc@pKlbAhChGxRfaAi@`r@eBrz@qL~|Aw@vQdD`_@zAzq@pCdu@hAho@hFt`@rFdt@lGtgApEtq@jBlQpHhh@nCxq@xEtbApD|u@x@jo@lAhSbD`YbCp~@hClh@j@~C??lKpk@A?rBdLdLdn@lQhbAzd@pjB~Dn^fHh[bJzX|j@bt@jTxErsAlmA~f@h{@fi@td@bG`SpJn[lEtOpD`Ut@pDjAfD|BdDjBtAbBx@nABrCOvBF|@BtDv@~BtBjB|En@pEUpEc@tC??yA|JdBqLVaBTqEo@qEhFyDpIuEpjAoTpMjCdfDj_AtnAbPuOnsAw@vQAdqCyGrp@kOpgC{U~aBaBhN_[rlCeLlYoJlN??sVv^g[da@_d@jo@gIjL_HnGgSrHsZBqY|EuQq@{Yo@gUKsMdXsItE}`@nLcz@r\\qr@~d@uc@tUiJ|EqI~G_GfFg[hUmJnDkCnBgAx@sBtDcA|EcAdIw\\dmD_DjVsFnS{G|R}H|O{T`YiJnLgYn`@_Ubw@sAxEoInY{FhNyGfKaEjG_EnF??{MnQkQrNmH|BmNdF_SzCkc@rCq`@{Ecf@yK{oAaXqM?eItEsSrOkc@``@il@|c@iIlG}XvSGB??qHpF?@q^zY_LxJoNlKwzAdnB{_@xf@c[|m@y]tgAeg@lgDuWzdCil@rmDyMncAkw@`_F_WlkC}NfpBwWnlBmNjz@_FdZy[fsAuRn`A}f@fzCge@ndBoSb`@aVn]qp@zu@eG`JuhAjbB{h@|o@q\\pa@}GlLmx@~~AuUd_@{s@~u@DNwGdFA@??oi@~a@_x@vm@i`@l]yWne@wg@~tAiLtJme@za@_[bc@ca@dj@iJdG_`@kIub@yQaZO_o@lVeTvFgRzAqb@]gOAsJjAce@fS}OtFeQdGeGlC_HfFqMpOaQhXwBjH??kQnl@m^lrAwt@hiBkRv[si@vk@qHpLqA`EeJbYuCdQ}CpRqIv{@yHljBgGhk@ei@nuC_V`eBm]zwAuDnGaI|MoH`FkS`DuJpEyU|ToS`[sRta@uOzd@wOr~@kGlj@eBtgAvAd}EcCnn@uHdl@oNh~A_CrWkE`iA{GpfAqBrk@oAryA_b@tnCaExPyJj\\i@jIwIvQ{c@foAoGfRcCvPqi@fyAgC`HgEdLkPnj@gUxg@eo@hlA_eCt`FmMhWsgAdpBiQj_@Vd@qAx@oLp\\_v@jcB{l@rsAie@jgA_j@naCsj@tzBcb@rjAaRzg@_TjoA@Iyq@tbCeGjEiwBqCoL_QaG~DwArKJrJaRRcIbJgSb[??_JbNoKxJoAJoFd@oKLO|@[n@c@^]Fg@G{Br]iFdVwEhL}V`^cKnOoc@xp@}BfDyFvIiBdCqApB??_FvHaNhVwk@r_Aod@pm@gGnH??sJnLqTnUoCxCwXnUyn@zh@m{@h{@{i@rm@me@tn@aEzF??eQrVkFfKoEfMmBfHkDfMiGf\\yC|WgBhW@ls@g@jVcBrMmD~MkG|I{FjEqAh@??iFvBeIhAuARsOxBwI|@gEVwCQuC_@gMiDgMeCoDw@kF}@yEIkn@tDsDl@{Af@sEbBeYzHgf@~Lw^nIkCK{VvL{@}EmC}J??eKu_@e]elA}DaNkAkA_B_FaJ__@??mC}KsFwWmTi|@iCaKaBeG??mG{UoCuOe@cD[aD_@qEzAw@`Ae@hDoAhNgCbCa@jMuLbOsMvSzt@rAfAlBj@r@{@z@[|@Dp@^n@|@`@tALhCEfA]~ArBlE~@hBdC|CN`@@D","direction":["inbound","inbound","inbound","inbound","inbound","inbound","inbound","inbound","inbound","inbound","inbound","inbound","inbound","inbound","inbound","inbound","inbound","inbound","inbound","inbound","inbound","inbound","inbound"]},{"routeId":"RT8","routeLinkIds":["RL119","RL120","RL121","RL122","RL123","RL124","RL125","RL126","RL127","RL128","RL129","RL130","RL131","RL132","RL133","RL134","RL135","RL136","RL137","RL138","RL139","RL140","RL141"],"description":"Tregaron, Square - Aberystwyth Bus Station Stand 5","stopPoints":["5230WDB23449","5230AWD71031","5230AWD71032","5230AWD71033","5230CGX16417","5230WDB23421","5230CGX16406","5230CGX16423","5230WDB47547","5230AWD71044","5230AWD71047","5230AWD71041","5230CGX16422","5230CGX16415","5230AWD71050","5230AWD71051","5230AWD71053","5230AWD71054","5230WDB23416","5230AWD71056","5230WDB48336","5230WDB22901","5230AWD71097","5230WDB25330"],"distance":[8937,373,2213,832,2463,3202,29,1508,1699,817,2445,1758,2804,1418,5508,391,261,546,358,566,215,148,322],"tracks":"wjfrbB~g`oFrCdDStHG^{CcB}Cn@kBdC{Fte@mBjMqBvKu@tEgM{`@iLaU}JmKmN_L_NkFoOmGwa@eKyR}Bma@gAmfAsDiEJafFc`AiWu@s_@hDi\\vCeXaBeq@wKuzA~Amd@qHec@sNaUuRkr@e{@uoAw|@yg@ih@c~@qeAab@g[k|@elAur@wy@adA_pB_H}MqYwc@{d@cj@gy@ke@gbAm{@yJmW}KaXaLaTaOal@aHaVaI{NmHeGmRiKwk@gf@wTwOi^}AqVwCsTmHci@g]_R_QmW}[o\\}_@sc@on@ks@csAm{@u}Bks@wtBmRgr@aOsq@yOga@kN{WyG}GeaAcs@{ToTm[ej@}Uaq@_Kwc@{f@a{D_DaN_c@aiAaPwX_\\u^mtA{lAoZqd@{^{p@_LqZmc@akCy]}kAib@seAmd@quAkd@}nAq[_|@}z@}gBcN_]ut@uiB{b@gv@_q@cu@yo@{c@gi@{g@_Oy[wDeWcKadAaCgV}Y_dCaJc]_OoZmQwMu]aTcVaQmi@ur@waAghAwc@iYih@so@cwAkhA}HiGuVcW{_@o`@mh@kp@c_@_`@at@kj@eZ{ZqQuKuj@gMsTY??iBE_Bk@q`@iVyNkIqSwVeMqM_GiCsIgBmK]kLbAqUhPeKtF_OtDeGb@??wJr@gW|@oHdCaFnCyKvMuN`^aMnp@q@nLZpjAuDrbAwD~^o~ApsIkR~t@g|@dfCciBlhGwEpPkBvPaB~[LhQr@nMxC~X~EpOhEbJ`FnKvHvZvG|]hGrc@|Gbc@hGta@pEjYtFbWnBjLb@vkAzD|_AlEtqBJzO??PfWrBj{@KlJ}@hL}d@v|CkThmBuv@d{CeUr`B}Ppp@cApKa@fFWdC??_@hDyArJeBtGmC~FoBvGcA|GaAfPiBdQqK`g@aIjh@oGxb@gEbQyFpRqEbLsGjPoFpI{EvFyF`DwTbEo]jGgNnB}GdAuGH_J\\yOq@mKe@kFk@yIeAgMcC}WiN{WeM}OcEwBEuGH_EjBoDpCmBpCkBhDgFrKoFpJaF`GcNfNcy@t`A{SbUgMlPwSnq@{Kjb@_Mnc@wC~KmCvMaB~QuAzTeA~QcAhTs@hREzQVhMHpEq@lRqAjRiAbRqB`LyBfJoCnHqFbIsEbEkTdKqs@nXsd@~L_ZdOgQnNmc@~e@u\\`TqI|Aul@sBil@pAeRdKig@|l@yV`IsTaCmKiA??wAO}q@gCwb@lEeo@`Skf@`[kIvDyl@dXcUxReSjWyP~Yie@feAke@~i@si@~\\ol@df@qHlAsg@eBso@lNcNpMa^~g@cJzRkBrHEhIrBx^yCrS_R~i@mT~ToF|CcRbCmj@iAiFpAsL`H_Rl]wPfOex@z`@gm@zD{EOeIuCmyAmh@{TqSySsV{UlZiDbQ`Ax[bAxIdKr|@aJrp@aVzmA_Ejk@unAcPefDk_AqMkCqjAnTqItEiFxDn@pEUpEc@tC??yA|JdBqLVaBTqEo@qEhFyDpIuEpjAoTpMjCdfDj_AtnAbPuOnsAw@vQAdqCyGrp@kOpgC{U~aBaBhN_[rlCeLlYoJlN??sVv^g[da@_d@jo@gIjL_HnGgSrHsZBqY|EuQq@{Yo@gUKsMdXsItE}`@nLcz@r\\qr@~d@uc@tUiJ|EqI~G_GfFg[hUmJnDkCnBgAx@sBtDcA|EcAdIw\\dmD_DjVsFnS{G|R}H|O{T`YiJnLgYn`@_Ubw@sAxEoInY{FhNyGfKaEjG_EnF??{MnQkQrNmH|BmNdF_SzCkc@rCq`@{Ecf@yK{oAaXqM?eItEsSrOkc@``@il@|c@iIlG}XvSGB??qHpFcn@_gBui@e`BwZ_{@aV_n@_n@_xAeg@stA{L_]kRg~@eSw|@MUf@b@BKg_By{Hiy@asGuMkxAqA_\\EiL{CrE}Vx^g]~v@uFlYuVznBsYhw@sZttAsF`OuSbXgUtKgWdEeWdMuIvF??_HrEsBtA}H`PgJ|Jo]dPaD~D_Ef]oCrDgD^sXgMwFbByT|YqOvb@kKzJe^pg@a_@lq@om@vUms@tx@}Of\\od@|g@il@dT{h@rJiDpBgNfI}E~BwFhp@E|qAhBt{@gCfm@AxWeB|I{MtSkBhS`JzoAMlMsHve@aAlG_D`JkHbJ{BbIf@dk@sI~DaD~DuFtGsF~Hm@vC??kOts@sPjcA_WneEzL|{@nLxf@pApPZpKmDhZqB`~@dBfs@vM|yAlMbjAbHvo@nHdi@dNfx@iDl{@uKvbDv@rd@}Cf`@dCxxBnDjqA`Frs@UxYfEb^p`@`~AjAxI\\ng@bCnLle@xhA`Uhb@zIbWnv@`tAjG|OzH~[v[jh@bSdj@vHptBLpXwMxpBiDvn@iApM~EiFDNwGdFA@??oi@~a@_x@vm@i`@l]yWne@wg@~tAiLtJme@za@_[bc@ca@dj@iJdG_`@kIub@yQaZO_o@lVeTvFgRzAqb@]gOAsJjAce@fS}OtFeQdGeGlC_HfFqMpOaQhXwBjH??kQnl@m^lrAwt@hiBkRv[si@vk@qHpLqA`EeJbYuCdQ}CpRqIv{@yHljBgGhk@ei@nuC_V`eBm]zwAuDnGaI|MoH`FkS`DuJpEyU|ToS`[sRta@uOzd@wOr~@kGlj@eBtgAvAd}EcCnn@uHdl@oNh~A_CrWkE`iA{GpfAqBrk@oAryA_b@tnCaExPyJj\\i@jIwIvQ{c@foAoGfRcCvPqi@fyAgC`HgEdLkPnj@gUxg@eo@hlA_eCt`FmMhWsgAdpBiQj_@Vd@qAx@oLp\\_v@jcB{l@rsAie@jgA_j@naCsj@tzBcb@rjAaRzg@_TjoA@Iyq@tbCeGjEiwBqCoL_QaG~DwArKJrJaRRcIbJgSb[??_JbNoKxJoAJoFd@oKLO|@[n@c@^]Fg@G{Br]iFdVwEhL}V`^cKnOoc@xp@}BfDyFvIiBdCqApB??_FvHaNhVwk@r_Aod@pm@gGnH??sJnLqTnUoCxCwXnUyn@zh@m{@h{@{i@rm@me@tn@aEzF??eQrVkFfKoEfMmBfHkDfMiGf\\yC|WgBhW@ls@g@jVcBrMmD~MkG|I{FjEqAh@??iFvBeIhAuARsOxBwI|@gEVwCQuC_@gMiDgMeCoDw@kF}@yEIkn@tDsDl@{Af@sEbBeYzHgf@~Lw^nIkCK{VvL{@}EmC}J??eKu_@e]elA}DaNkAkA_B_FaJ__@??mC}KsFwWmTi|@iCaKaBeG??mG{UoCuOe@cD[aD_@qEzAw@`Ae@hDoAhNgCbCa@jMuLbOsMvSzt@rAfAlBj@r@{@z@[|@Dp@^n@|@`@tALhCEfA]~ArBlE~@hBdC|CN`@@D","direction":["inbound","inbound","inbound","inbound","inbound","inbound","inbound","inbound","inbound","inbound","inbound","inbound","inbound","inbound","inbound","inbound","inbound","inbound","inbound","inbound","inbound","inbound","inbound"]},{"routeId":"RT9","routeLinkIds":["RL142","RL143","RL144","RL145","RL146","RL147","RL148","RL149","RL150","RL151","RL152","RL153","RL154","RL155","RL156","RL157","RL158","RL159","RL160","RL161","RL162","RL163","RL164","RL165"],"description":"Ystrad Meurig - Aberystwyth Bus Station Stand 5","stopPoints":["5230AWD71034","5230CGX16407","5230CGX16408","5230AWD71032","5230CGX16411","5230CGX16412","5230AWD71039","5230CGX16355","5230WDB23420","5230CGX16406","5230CGX16423","5230WDB47547","5230AWD71044","5230AWD71047","5230CGX16415","5230AWD71050","5230AWD71051","5230AWD71053","5230AWD71054","5230WDB23416","5230AWD71056","5230WDB48336","5230WDB22901","5230AWD71097","5230WDB25330"],"distance":[837,2207,54,1698,3811,1462,2155,3907,1156,29,1508,1699,817,3403,1418,5508,391,261,546,358,566,215,148,322],"tracks":"{vrvbBrddmFZwC`@gFbAqK|Pqp@dUs`Btv@e{CjTimB|d@w|C|@iLJmJsBk{@S{[??IgKmEuqB{D}_Ac@wkAoBkLuFcWqEkYiGua@}Gcc@iGsc@wG}]wHwZaFoKiEcJ_FqOyC_Ys@oMMiQ`B_\\jBwPvEqPbiBmhGf|@efCjR_u@n~AqsIvD__@tDsbA[qjAp@oL`Mop@tNa^xKwM`FoCnHeCfW}@nJq@??lGe@vEmA}MpBwJr@gW|@uCuIwDoHw]qe@iJiMyHeF_VcRq`@uJchAsMwVQoQzDaZtLuYrOcR`QiRjNkGb@}GSyG{BiQ{LyTuRkRaSax@a~@_NiV{Lk]yMy[kOse@qMyf@m^o`BqRe`Acs@suBa`@ktAmCiM??mCiMcE{RuGyS{GgTeJkUwLwPkZmXsUqVqQm@ueBvq@ad@dVg^xW}DnCyYjS{_Adp@mSzJsk@rLua@t@mk@sI_^yNir@ki@uYkSuVuEo\\OeQpFmY`SqPfVs]zi@kl@t_AkMhRwQpMoh@fZ}U~KsTfO_RdNqR|HcR`I_GhI}ClKyE|Uu@vK[lPy@zm@uHlb@_Nb[om@fm@cVfSyYbQyi@tQko@|IwV`AuTeAqR}FmVwKyMgEaVvJuWPm]wBuHe@oe@iBqj@zBwUxGiKbFmKvCg]\\sb@|DaJzFwIpOsInUgI`SoKjIgNbBqQlH_Q~Ig^xVgg@bLyd@zMuRbNqJ|@??o@FeLl@yGEoNtC_\\~LwJ}LiLkPuNiQkUcZ{Q_Q{Tkd@qP{c@_K_m@wHmf@cA}UpA{MfByMcH_YeNsUwjBocBiO_b@uI}o@kLyViWch@mTaX{VqVaMsZeDkImEcDqDbAkCdIcApKsAxT}CdGsDxCkFNsEmCuGoCgR_Mi[cMeIgA??_k@sHub@eDqZqFm[iIwYwKsMeX{HgWoDwYoDov@iCkIoJoDsEoAgEdLeBbVEp[jFf^X`N|@j`@`I``@rEpDfJ`PnRzi@o@|PwChSaKh[uRlVo^~Qo\\|i@sH|]oMbZWvb@xEd`CjE~]nE`_@|GlkAmAnYaBvIiKnPmRbRiN`Nof@jj@wMtSkLbRyL`d@_K`w@cEjYeOn`@wg@~i@ua@baAgBjK??uB|LkBdk@}Cn]wRfqAiTz_AmW~|@xg@bh@vCdHjGt_@nMt\\xAtIdE|cAnGv]~C~h@dDzRtZdkAhNpRtBnGnB`IT~SjGbYnWfb@zIbYlBjRzBxt@jJb|@_Ejd@GvOfCtNdJzTrQvsAzHrb@fN|e@xC|DxV~Mh]|YlOjt@?hl@qG`r@}Abg@Af]rCfhByArpAoLzaA_MvbA}Iv_@g@zr@tAfd@|Fhh@nE~i@fE~fA@nc@pKlbAhChGxRfaAi@`r@eBrz@qL~|Aw@vQdD`_@zAzq@pCdu@hAho@hFt`@rFdt@lGtgApEtq@jBlQpHhh@nCxq@xEtbApD|u@x@jo@lAhSbD`YbCp~@hClh@j@~C??lKpk@A?rBdLdLdn@lQhbAzd@pjB~Dn^fHh[bJzX|j@bt@jTxErsAlmA~f@h{@fi@td@bG`SpJn[lEtOpD`Ut@pDjAfD|BdDjBtAbBx@nABrCOvBF|@BtDv@~BtBjB|En@pEUpEc@tC??yA|JdBqLVaBTqEo@qEhFyDpIuEpjAoTpMjCdfDj_AtnAbPuOnsAw@vQAdqCyGrp@kOpgC{U~aBaBhN_[rlCeLlYoJlN??sVv^g[da@_d@jo@gIjL_HnGgSrHsZBqY|EuQq@{Yo@gUKsMdXsItE}`@nLcz@r\\qr@~d@uc@tUiJ|EqI~G_GfFg[hUmJnDkCnBgAx@sBtDcA|EcAdIw\\dmD_DjVsFnS{G|R}H|O{T`YiJnLgYn`@_Ubw@sAxEoInY{FhNyGfKaEjG_EnF??{MnQkQrNmH|BmNdF_SzCkc@rCq`@{Ecf@yK{oAaXqM?eItEsSrOkc@``@il@|c@iIlG}XvSGB??qHpF?@q^zY_LxJoNlKwzAdnB{_@xf@c[|m@y]tgAeg@lgDuWzdCil@rmDyMncAkw@`_F_WlkC}NfpBwWnlBmNjz@_FdZy[fsAuRn`A}f@fzCge@ndBoSb`@aVn]qp@zu@eG`JuhAjbB{h@|o@q\\pa@}GlLmx@~~AuUd_@{s@~u@DNwGdFA@??oi@~a@_x@vm@i`@l]yWne@wg@~tAiLtJme@za@_[bc@ca@dj@iJdG_`@kIub@yQaZO_o@lVeTvFgRzAqb@]gOAsJjAce@fS}OtFeQdGeGlC_HfFqMpOaQhXwBjH??kQnl@m^lrAwt@hiBkRv[si@vk@qHpLqA`EeJbYuCdQ}CpRqIv{@yHljBgGhk@ei@nuC_V`eBm]zwAuDnGaI|MoH`FkS`DuJpEyU|ToS`[sRta@uOzd@wOr~@kGlj@eBtgAvAd}EcCnn@uHdl@oNh~A_CrWkE`iA{GpfAqBrk@oAryA_b@tnCaExPyJj\\i@jIwIvQ{c@foAoGfRcCvPqi@fyAgC`HgEdLkPnj@gUxg@eo@hlA_eCt`FmMhWsgAdpBiQj_@Vd@qAx@oLp\\_v@jcB{l@rsAie@jgA_j@naCsj@tzBcb@rjAaRzg@_TjoA@Iyq@tbCeGjEiwBqCoL_QaG~DwArKJrJaRRcIbJgSb[??_JbNoKxJoAJoFd@oKLO|@[n@c@^]Fg@G{Br]iFdVwEhL}V`^cKnOoc@xp@}BfDyFvIiBdCqApB??_FvHaNhVwk@r_Aod@pm@gGnH??sJnLqTnUoCxCwXnUyn@zh@m{@h{@{i@rm@me@tn@aEzF??eQrVkFfKoEfMmBfHkDfMiGf\\yC|WgBhW@ls@g@jVcBrMmD~MkG|I{FjEqAh@??iFvBeIhAuARsOxBwI|@gEVwCQuC_@gMiDgMeCoDw@kF}@yEIkn@tDsDl@{Af@sEbBeYzHgf@~Lw^nIkCK{VvL{@}EmC}J??eKu_@e]elA}DaNkAkA_B_FaJ__@??mC}KsFwWmTi|@iCaKaBeG??mG{UoCuOe@cD[aD_@qEzAw@`Ae@hDoAhNgCbCa@jMuLbOsMvSzt@rAfAlBj@r@{@z@[|@Dp@^n@|@`@tALhCEfA]~ArBlE~@hBdC|CN`@@D","direction":["inbound","inbound","inbound","inbound","inbound","inbound","inbound","inbound","inbound","inbound","inbound","inbound","inbound","inbound","inbound","inbound","inbound","inbound","inbound","inbound","inbound","inbound","inbound","inbound"]},{"routeId":"RT10","routeLinkIds":["RL166","RL167","RL168","RL169","RL170","RL171","RL172","RL173","RL174","RL175","RL176","RL177","RL178","RL179","RL180","RL181","RL182","RL183","RL184","RL185","RL186","RL187","RL188","RL189"],"description":"Ysgol Henry Richard - Aberystwyth Bus Station Stand 5","stopPoints":["5230WDB46530","5230AWD71030","5230WDB23449","5230WDB47544","5230AWD71035","5230AWD71034","5230CGX16407","5230CGX16417","5230WDB23421","5230CGX16406","5230CGX16423","5230WDB47547","5230AWD71044","5230AWD71047","5230CGX16415","5230AWD71050","5230AWD71051","5230AWD71053","5230AWD71054","5230WDB23416","5230AWD71056","5230WDB48336","5230WDB22901","5230AWD71097","5230WDB25330"],"distance":[673,30,3372,6355,1829,837,888,2463,3202,29,1508,1699,817,3403,1418,5508,391,261,546,358,566,215,148,322],"tracks":"axdrbB~cjoFsGnv@{@xXvFzSsH|M?lA_@kAD@@ArA{b@z@yXzJmkA~FeRsFoJkNm[wKce@_Is^_DyM{I}RoIoPyN_Vt@uEpBwKlBkMzFue@p@_A??x@eA?cM@G|Cc@`@f@??rCdDStHG^{CcB}Cn@kBdC{Fte@mBjMqBvKu@tE{Hvb@uDrGaDxBeCv@kDr@cNt@_z@~FiSCyNMmk@pCkVzCkVxEuWlIaSnI_YfQajBlyA_SnQeP|NeGdGeTfTqt@`_AeyBhrCoDtCiE`EaQ`Zw`@z~@s^xo@}R|WuQjMmPpPsIpNm\\bv@kGhQuPtb@kIxUcPj]iVbe@sPtSio@xw@aOxI{KlJcQnTgJ|P{FtPeA|GYxMLdMlAtZZnWa@tRuAdKmBhJuH`UwUvh@oI~MoGfKgLtLmJvJwH|KgJlNiHbNeBxGwCbP_Hz`@{I~e@sPvz@yH|XkG~L_FtHaHjHoHlEwG|Ds[nNyJvDkIvByJp@eYhAmQl@sL\\uE|@??mEx@}JxBw`@dIyH`AsFSeGi@aJeBoKmAoPg@_MBeUl@eO}@oUgAaINmWtG{WjH}OpF_H|DeGhIsF~HeGjGsHnCwHn@oJVuKxBmCpC_MsGwEkEkBaHoB_M_Fa\\yIge@_CaNuD_HqIoKcQ{ToCoGkFqL_FgFsGcDcIwAuN}AuZcDkKJyFzEkR`UwHrHyN`FiTnDsQnEwNtG{JdJiBnDcCfIgH|XkIb\\kDdJwEtDkHjB}MnCmJhFgF`EiG~KeIzQ}Kx[qhCmZqWi`@aV}EsdAcz@mKsIwrA{i@ggA`Oql@cQgFaJiGaPiCyKwCsQgCgMyGmKmFwEwJ{H_LuEmMlA{GtB}FzBsFcE}GgKeGmJgCkGaB}JyEmYqJ_\\sJgYoFuQuDiWyLyu@qGad@wJaa@qIwWwHuQ}Sm]uBoCuH}JaG_I{CsHgFiNuJyRwH{P}CcEyKuDcXwEsLaB{NOsK|Aed@xDe[~CcPpAaQzBwNXaHgAaPcE}DmGaHeLeIaQkEyHaJ}IgPiOcWwTyh@s^eOsKwJcK}HiSeEkPcDaQkGqOwJ_S}E{KgHoHiKqLuFaLeEwS}CoSeF{JmFyI}B}NwCsScDyTyF_]kFyTyBwKiCoHkD_GuF_JmCcGoDuKwCsOa@qQx@ua@zAco@n@yYWaV}@}QqAqT{BwXcA{\\yHa}@}Gae@eGw[kDeXaC{c@eE_aAkBoe@oBix@o@oc@k@e\\cAqTgFiUwE_Qs_@uiAyJoZuGi\\yHgd@}Iah@qHse@{Ima@oGkXoFmOgGaPkCeM{AeTqAoXC{YFc]r@uYlBsZpC}TlEaVxGgZnBgWn@cQK{HsEgNaRia@sI{V_FuNuHcNwA{D??aAkCwDgKyHaZoEgS_HuRsH_QcMoRaL_P}GyLcEiOaCiQ}EsP}H{N{HsLyMuRwFiKkEsLaFiRiCePmDkQcFuQ}GaPmGmOaEyPgAyF{CkOiFuXyC}LoEiKmKqQiMaT_NkUcWo^cTqVkNsPmNsMyIyOuGqLwLu]kKsU_JsNkEoG}LuHqQoLeOyIeMcFoNcHsToGsk@yRo\\sMeFuCcG_EiEwFqDuFsDcKuCkJsDyIy[mVcHsFuFuA{EUcIPcHB{I[a]mHkKuBkXiHdBuGxAsJZwC??ZwC`@gFbAqK|Pqp@dUs`Btv@e{CjTimB|d@w|C|@iLJmJsBk{@S{[??IgKlNzToMfRrBj{@KlJ}@hL}d@v|CkThmBuv@d{CeUr`B}Ppp@cApKa@fFWdC??_@hDyArJeBtGmC~FoBvGcA|GaAfPiBdQqK`g@aIjh@oGxb@gEbQyFpRqEbLsGjPoFpI{EvFyF`DwTbEo]jGgNnB}GdAuGH_J\\yOq@mKe@kFk@yIeAgMcC}WiN{WeM}OcEwBEuGH_EjBoDpCmBpCkBhDgFrKoFpJaF`GcNfNcy@t`A{SbUgMlPwSnq@{Kjb@_Mnc@wC~KmCvMaB~QuAzTeA~QcAhTs@hREzQVhMHpEq@lRqAjRiAbRqB`LyBfJoCnHqFbIsEbEkTdKqs@nXsd@~L_ZdOgQnNmc@~e@u\\`TqI|Aul@sBil@pAeRdKig@|l@yV`IsTaCmKiA??wAO}q@gCwb@lEeo@`Skf@`[kIvDyl@dXcUxReSjWyP~Yie@feAke@~i@si@~\\ol@df@qHlAsg@eBso@lNcNpMa^~g@cJzRkBrHEhIrBx^yCrS_R~i@mT~ToF|CcRbCmj@iAiFpAsL`H_Rl]wPfOex@z`@gm@zD{EOeIuCmyAmh@{TqSySsV{UlZiDbQ`Ax[bAxIdKr|@aJrp@aVzmA_Ejk@unAcPefDk_AqMkCqjAnTqItEiFxDn@pEUpEc@tC??yA|JdBqLVaBTqEo@qEhFyDpIuEpjAoTpMjCdfDj_AtnAbPuOnsAw@vQAdqCyGrp@kOpgC{U~aBaBhN_[rlCeLlYoJlN??sVv^g[da@_d@jo@gIjL_HnGgSrHsZBqY|EuQq@{Yo@gUKsMdXsItE}`@nLcz@r\\qr@~d@uc@tUiJ|EqI~G_GfFg[hUmJnDkCnBgAx@sBtDcA|EcAdIw\\dmD_DjVsFnS{G|R}H|O{T`YiJnLgYn`@_Ubw@sAxEoInY{FhNyGfKaEjG_EnF??{MnQkQrNmH|BmNdF_SzCkc@rCq`@{Ecf@yK{oAaXqM?eItEsSrOkc@``@il@|c@iIlG}XvSGB??qHpF?@q^zY_LxJoNlKwzAdnB{_@xf@c[|m@y]tgAeg@lgDuWzdCil@rmDyMncAkw@`_F_WlkC}NfpBwWnlBmNjz@_FdZy[fsAuRn`A}f@fzCge@ndBoSb`@aVn]qp@zu@eG`JuhAjbB{h@|o@q\\pa@}GlLmx@~~AuUd_@{s@~u@DNwGdFA@??oi@~a@_x@vm@i`@l]yWne@wg@~tAiLtJme@za@_[bc@ca@dj@iJdG_`@kIub@yQaZO_o@lVeTvFgRzAqb@]gOAsJjAce@fS}OtFeQdGeGlC_HfFqMpOaQhXwBjH??kQnl@m^lrAwt@hiBkRv[si@vk@qHpLqA`EeJbYuCdQ}CpRqIv{@yHljBgGhk@ei@nuC_V`eBm]zwAuDnGaI|MoH`FkS`DuJpEyU|ToS`[sRta@uOzd@wOr~@kGlj@eBtgAvAd}EcCnn@uHdl@oNh~A_CrWkE`iA{GpfAqBrk@oAryA_b@tnCaExPyJj\\i@jIwIvQ{c@foAoGfRcCvPqi@fyAgC`HgEdLkPnj@gUxg@eo@hlA_eCt`FmMhWsgAdpBiQj_@Vd@qAx@oLp\\_v@jcB{l@rsAie@jgA_j@naCsj@tzBcb@rjAaRzg@_TjoA@Iyq@tbCeGjEiwBqCoL_QaG~DwArKJrJaRRcIbJgSb[??_JbNoKxJoAJoFd@oKLO|@[n@c@^]Fg@G{Br]iFdVwEhL}V`^cKnOoc@xp@}BfDyFvIiBdCqApB??_FvHaNhVwk@r_Aod@pm@gGnH??sJnLqTnUoCxCwXnUyn@zh@m{@h{@{i@rm@me@tn@aEzF??eQrVkFfKoEfMmBfHkDfMiGf\\yC|WgBhW@ls@g@jVcBrMmD~MkG|I{FjEqAh@??iFvBeIhAuARsOxBwI|@gEVwCQuC_@gMiDgMeCoDw@kF}@yEIkn@tDsDl@{Af@sEbBeYzHgf@~Lw^nIkCK{VvL{@}EmC}J??eKu_@e]elA}DaNkAkA_B_FaJ__@??mC}KsFwWmTi|@iCaKaBeG??mG{UoCuOe@cD[aD_@qEzAw@`Ae@hDoAhNgCbCa@jMuLbOsMvSzt@rAfAlBj@r@{@z@[|@Dp@^n@|@`@tALhCEfA]~ArBlE~@hBdC|CN`@@D","direction":["inbound","inbound","inbound","inbound","inbound","inbound","inbound","inbound","inbound","inbound","inbound","inbound","inbound","inbound","inbound","inbound","inbound","inbound","inbound","inbound","inbound","inbound","inbound","inbound"]}],"timetables":{"JP_EVAT021-11":[{"destinationDisplay":"Talbot Hotel","direction":"outbound","routeLinkId":["RL36","RL37","RL38","RL39","RL40","RL41","RL42","RL43","RL44","RL45","RL46","RL47","RL48","RL49","RL50","RL51","RL52","RL53","RL54","RL55"],"stopPoints":["5230WDB25330","5230CGX16447","5230CGX16359","5230AWD71055","5230AWD71057","5230AWD71058","5230CGX16402","5230AWD71048","5230CGX16416","5230CGX16405","5230WDB47548","5230CGX16406","5230CGX16423","5230WDB23420","5230AWD71040","5230CGX16612","5230AWD71038","5230AWD71037","5230CGX16408","5230CGX16409","5230AWD71030"],"runtimes":["PT1M","PT1M","PT1M","PT1M","PT1M","PT7M","PT1M","PT4M","PT0S","PT2M","PT2M","PT1M","PT2M","PT6M","PT2M","PT3M","PT7M","PT3M","PT0S","PT20M"],"activities":["pickUp","pickUpAndSetDown","pickUpAndSetDown","pickUpAndSetDown","pickUpAndSetDown","pickUpAndSetDown","pickUpAndSetDown","pickUpAndSetDown","pickUpAndSetDown","pickUpAndSetDown","pickUpAndSetDown","pickUpAndSetDown","pickUpAndSetDown","pickUpAndSetDown","pickUpAndSetDown","pickUpAndSetDown","pickUpAndSetDown","pickUpAndSetDown","pickUpAndSetDown","pickUpAndSetDown","pickUpAndSetDown"],"waitTimes":["","","","","","","","","","","","","","","","","","","","",""],"timingStatuses":["PTP","OTH","PTP","OTH","OTH","PTP","PTP","OTH","PTP","OTH","PTP","OTH","PTP","PTP","PTP","PTP","PTP","PTP","PTP","OTH","PTP"],"sequenceNumber":["1","2","3","4","5","6","7","8","12","13","14","15","16","17","18","19","20","21","25","30","31"],"dynamicDestinationDisplay":["","","","","","","","","","","","","","","","","","","","",""],"lineId":"SL1","note":[],"vehicle":"","schedules":[{"profiles":{"regular":["Monday","Wednesday","Friday"],"holidays":{"notRunning":["Christmas","GoodFriday","NewYearsDay","LateSummerBankHolidayNotScotland","MayDay","EasterMonday","SpringBank"]}},"departures":["17:40:00"],"dayShift":[0]}]}],"JP_EVAT021-12":[{"destinationDisplay":"Aberystwyth Bus Station Stand 5","direction":"inbound","routeLinkId":["RL166","RL167","RL168","RL169","RL170","RL171","RL172","RL173","RL174","RL175","RL176","RL177","RL178","RL179","RL180","RL181","RL182","RL183","RL184","RL185","RL186","RL187","RL188","RL189"],"stopPoints":["5230WDB46530","5230AWD71030","5230WDB23449","5230WDB47544","5230AWD71035","5230AWD71034","5230CGX16407","5230CGX16417","5230WDB23421","5230CGX16406","5230CGX16423","5230WDB47547","5230AWD71044","5230AWD71047","5230CGX16415","5230AWD71050","5230AWD71051","5230AWD71053","5230AWD71054","5230WDB23416","5230AWD71056","5230WDB48336","5230WDB22901","5230AWD71097","5230WDB25330"],"runtimes":["PT0S","PT1M","PT6M","PT10M","PT1M","PT0S","PT2M","PT3M","PT9M","PT1M","PT2M","PT2M","PT2M","PT2M","PT1M","PT10M","PT1M","PT1M","PT1M","PT2M","PT1M","PT1M","PT1M","PT1M"],"activities":["pickUp","pickUpAndSetDown","pickUpAndSetDown","pickUpAndSetDown","pickUpAndSetDown","pickUpAndSetDown","pickUpAndSetDown","pickUpAndSetDown","pickUpAndSetDown","pickUpAndSetDown","pickUpAndSetDown","pickUpAndSetDown","pickUpAndSetDown","pickUpAndSetDown","pickUpAndSetDown","pickUpAndSetDown","pickUpAndSetDown","pickUpAndSetDown","pickUpAndSetDown","pickUpAndSetDown","pickUpAndSetDown","pickUpAndSetDown","pickUpAndSetDown","pickUpAndSetDown","pickUpAndSetDown"],"waitTimes":["","","","","","","","","","","","","","","","","","","","","","","","",""],"timingStatuses":["PTP","OTH","PTP","PTP","PTP","PTP","OTH","OTH","PTP","OTH","PTP","PTP","OTH","PTP","OTH","PTP","PTP","OTH","OTH","OTH","PTP","OTH","OTH","OTH","PTP"],"sequenceNumber":["1","2","3","5","6","7","8","12","13","19","20","21","22","23","26","27","28","29","30","31","32","33","34","35","36"],"dynamicDestinationDisplay":["","","","","","","","","","","","","","","","","","","","","","","","",""],"lineId":"SL1","note":[],"vehicle":"","schedules":[{"profiles":{"regular":["MondayToFriday"],"holidays":{"notRunning":["Christmas","GoodFriday","NewYearsDay","LateSummerBankHolidayNotScotland","MayDay","EasterMonday","SpringBank"]},"servicedOrganisations":{"notRunning":[{"WorkingDays":{"ServicedOrganisationRef":"SDB"}}]}},"departures":["15:45:00"],"dayShift":[0]}]}],"RT1":[{"destinationDisplay":"Talbot Hotel","direction":"outbound","routeLinkId":["RL1","RL2","RL3","RL4","RL5","RL6","RL7","RL8","RL9"],"stopPoints":["5230WDB47548","5230CGX16406","5230CGX16423","5230AWD71036","5230AWD71034","5230CGX16407","5230CGX16417","5230CGX16484","5230WDB47545","5230AWD71030"],"runtimes":["PT4M","PT1M","PT7M","PT5M","PT3M","PT0S","PT3M","PT8M","PT8M"],"activities":["pickUp","pickUpAndSetDown","pickUpAndSetDown","pickUpAndSetDown","pickUpAndSetDown","pickUpAndSetDown","pickUpAndSetDown","pickUpAndSetDown","pickUpAndSetDown","pickUpAndSetDown"],"waitTimes":["","","","","","","","","",""],"timingStatuses":["PTP","OTH","PTP","PTP","OTH","PTP","OTH","PTP","PTP","PTP"],"sequenceNumber":["14","15","16","22","23","24","26","27","28","31"],"dynamicDestinationDisplay":["","","","","","","","","",""],"lineId":"SL1","note":[],"vehicle":"","schedules":[{"profiles":{"regular":["MondayToFriday"],"holidays":{"notRunning":["Christmas","GoodFriday","NewYearsDay","LateSummerBankHolidayNotScotland","MayDay","EasterMonday","SpringBank"]},"servicedOrganisations":{"notRunning":[{"WorkingDays":{"ServicedOrganisationRef":"SDB"}}]}},"departures":["08:05:00"],"dayShift":[0]}]}],"RT10":[{"destinationDisplay":"Aberystwyth Bus Station Stand 5","direction":"inbound","routeLinkId":["RL166","RL167","RL168","RL169","RL170","RL171","RL172","RL173","RL174","RL175","RL176","RL177","RL178","RL179","RL180","RL181","RL182","RL183","RL184","RL185","RL186","RL187","RL188","RL189"],"stopPoints":["5230WDB46530","5230AWD71030","5230WDB23449","5230WDB47544","5230AWD71035","5230AWD71034","5230CGX16407","5230CGX16417","5230WDB23421","5230CGX16406","5230CGX16423","5230WDB47547","5230AWD71044","5230AWD71047","5230CGX16415","5230AWD71050","5230AWD71051","5230AWD71053","5230AWD71054","5230WDB23416","5230AWD71056","5230WDB48336","5230WDB22901","5230AWD71097","5230WDB25330"],"runtimes":["PT0S","PT1M","PT6M","PT10M","PT1M","PT0S","PT2M","PT3M","PT9M","PT1M","PT2M","PT2M","PT2M","PT2M","PT1M","PT10M","PT1M","PT0S","PT2M","PT1M","PT2M","PT1M","PT0S","PT2M"],"activities":["pickUp","pickUpAndSetDown","pickUpAndSetDown","pickUpAndSetDown","pickUpAndSetDown","pickUpAndSetDown","pickUpAndSetDown","pickUpAndSetDown","pickUpAndSetDown","pickUpAndSetDown","pickUpAndSetDown","pickUpAndSetDown","pickUpAndSetDown","pickUpAndSetDown","pickUpAndSetDown","pickUpAndSetDown","pickUpAndSetDown","pickUpAndSetDown","pickUpAndSetDown","pickUpAndSetDown","pickUpAndSetDown","pickUpAndSetDown","pickUpAndSetDown","pickUpAndSetDown","pickUpAndSetDown"],"waitTimes":["","","","","","","","","","","","","","","","","","","","","","","","",""],"timingStatuses":["PTP","OTH","PTP","PTP","PTP","PTP","OTH","OTH","PTP","OTH","PTP","PTP","OTH","PTP","OTH","PTP","PTP","OTH","OTH","OTH","PTP","OTH","OTH","OTH","PTP"],"sequenceNumber":["1","2","3","5","6","7","8","12","13","19","20","21","22","23","26","27","28","29","30","31","32","33","34","35","36"],"dynamicDestinationDisplay":["","","","","","","","","","","","","","","","","","","","","","","","",""],"lineId":"SL1","note":[],"vehicle":"","schedules":[{"profiles":{"regular":["MondayToFriday"],"holidays":{"notRunning":["Christmas","GoodFriday","NewYearsDay","LateSummerBankHolidayNotScotland","MayDay","EasterMonday","SpringBank"]},"servicedOrganisations":{"running":[{"WorkingDays":{"ServicedOrganisationRef":"SDB"}}]}},"departures":["15:44:00"],"dayShift":[0]}]}],"RT2":[{"destinationDisplay":"Talbot Hotel","direction":"outbound","routeLinkId":["RL10","RL11","RL12","RL13","RL14","RL15","RL16","RL17","RL18","RL19"],"stopPoints":["5230WDB47548","5230CGX16406","5230CGX16423","5230AWD71036","5230AWD71034","5230CGX16407","5230CGX16417","5230CGX16484","5230WDB47545","5230WDB46530","5230AWD71030"],"runtimes":["PT4M","PT1M","PT7M","PT5M","PT3M","PT0S","PT3M","PT8M","PT7M","PT1M"],"activities":["pickUp","pickUpAndSetDown","pickUpAndSetDown","pickUpAndSetDown","pickUpAndSetDown","pickUpAndSetDown","pickUpAndSetDown","pickUpAndSetDown","pickUpAndSetDown","pickUpAndSetDown","pickUpAndSetDown"],"waitTimes":["","","","","","","","","","",""],"timingStatuses":["PTP","OTH","PTP","PTP","OTH","PTP","OTH","PTP","PTP","PTP","PTP"],"sequenceNumber":["14","15","16","22","23","24","26","27","28","29","31"],"dynamicDestinationDisplay":["","","","","","","","","","",""],"lineId":"SL1","note":[],"vehicle":"","schedules":[{"profiles":{"regular":["MondayToFriday"],"holidays":{"notRunning":["Christmas","GoodFriday","NewYearsDay","LateSummerBankHolidayNotScotland","MayDay","EasterMonday","SpringBank"]},"servicedOrganisations":{"running":[{"WorkingDays":{"ServicedOrganisationRef":"SDB"}}]}},"departures":["08:05:00"],"dayShift":[0]}]}],"RT3":[{"destinationDisplay":"Wellington House","direction":"outbound","routeLinkId":["RL20","RL21","RL22","RL23","RL24","RL25","RL26","RL27","RL28","RL29","RL30","RL31","RL32","RL33","RL34","RL35"],"stopPoints":["5230WDB25330","5230CGX16447","5230CGX16359","5230AWD71055","5230AWD71057","5230AWD71058","5230CGX16402","5230AWD71048","5230CGX16416","5230CGX16405","5230WDB47548","5230CGX16406","5230CGX16423","5230AWD71036","5230AWD71034","5230CGX16407","5230CGX16408"],"runtimes":["PT1M","PT1M","PT1M","PT1M","PT1M","PT7M","PT1M","PT4M","PT0S","PT2M","PT2M","PT1M","PT5M","PT1M","PT1M","PT6M"],"activities":["pickUp","pickUpAndSetDown","pickUpAndSetDown","pickUpAndSetDown","pickUpAndSetDown","pickUpAndSetDown","pickUpAndSetDown","pickUpAndSetDown","pickUpAndSetDown","pickUpAndSetDown","pickUpAndSetDown","pickUpAndSetDown","pickUpAndSetDown","pickUpAndSetDown","pickUpAndSetDown","pickUpAndSetDown","pickUpAndSetDown"],"waitTimes":["","","","","","","","","","","","","","","","",""],"timingStatuses":["PTP","OTH","PTP","OTH","OTH","PTP","PTP","OTH","PTP","OTH","PTP","OTH","PTP","PTP","OTH","PTP","PTP"],"sequenceNumber":["1","2","3","4","5","6","7","8","12","13","14","15","16","22","23","24","25"],"dynamicDestinationDisplay":["","","","","","","","","","","","","","","","",""],"lineId":"SL1","note":[],"vehicle":"","schedules":[{"profiles":{"regular":["MondayToFriday"],"holidays":{"notRunning":["Christmas","GoodFriday","NewYearsDay","LateSummerBankHolidayNotScotland","MayDay","EasterMonday","SpringBank"]}},"departures":["12:15:00"],"dayShift":[0]}]}],"RT4":[{"destinationDisplay":"Talbot Hotel","direction":"outbound","routeLinkId":["RL36","RL37","RL38","RL39","RL40","RL41","RL42","RL43","RL44","RL45","RL46","RL47","RL48","RL49","RL50","RL51","RL52","RL53","RL54","RL55"],"stopPoints":["5230WDB25330","5230CGX16447","5230CGX16359","5230AWD71055","5230AWD71057","5230AWD71058","5230CGX16402","5230AWD71048","5230CGX16416","5230CGX16405","5230WDB47548","5230CGX16406","5230CGX16423","5230WDB23420","5230AWD71040","5230CGX16612","5230AWD71038","5230AWD71037","5230CGX16408","5230CGX16409","5230AWD71030"],"runtimes":["PT1M","PT1M","PT1M","PT1M","PT1M","PT7M","PT3M","PT7M","PT0S","PT2M","PT2M","PT1M","PT2M","PT6M","PT2M","PT3M","PT7M","PT3M","PT0S","PT20M"],"activities":["pickUp","pickUpAndSetDown","pickUpAndSetDown","pickUpAndSetDown","pickUpAndSetDown","pickUpAndSetDown","pickUpAndSetDown","pickUpAndSetDown","pickUpAndSetDown","pickUpAndSetDown","pickUpAndSetDown","pickUpAndSetDown","pickUpAndSetDown","pickUpAndSetDown","pickUpAndSetDown","pickUpAndSetDown","pickUpAndSetDown","pickUpAndSetDown","pickUpAndSetDown","pickUpAndSetDown","pickUpAndSetDown"],"waitTimes":["","","","","","","","","","","","","","","","","","","","",""],"timingStatuses":["PTP","OTH","PTP","OTH","OTH","PTP","PTP","OTH","PTP","OTH","PTP","OTH","PTP","PTP","PTP","PTP","PTP","PTP","PTP","OTH","PTP"],"sequenceNumber":["1","2","3","4","5","6","7","8","12","13","14","15","16","17","18","19","20","21","25","30","31"],"dynamicDestinationDisplay":["","","","","","","","","","","","","","","","","","","","",""],"lineId":"SL1","note":[],"vehicle":"","schedules":[{"profiles":{"regular":["Monday","Wednesday","Friday"],"holidays":{"notRunning":["Christmas","GoodFriday","NewYearsDay","LateSummerBankHolidayNotScotland","MayDay","EasterMonday","SpringBank"]}},"departures":["14:05:00"],"dayShift":[0]}]}],"RT5":[{"destinationDisplay":"Talbot Hotel","direction":"outbound","routeLinkId":["RL56","RL57","RL58","RL59","RL60","RL61","RL62","RL63","RL64","RL65","RL66","RL67","RL68","RL69","RL70","RL71","RL72","RL73","RL74","RL75","RL76"],"stopPoints":["5230WDB25330","5230CGX16447","5230CGX16359","5230AWD71055","5230AWD71057","5230AWD71058","5230CGX16402","5230AWD71048","5230AWD71049","5230CGX16403","5230CGX16404","5230CGX16416","5230CGX16405","5230WDB47548","5230CGX16406","5230CGX16423","5230AWD71036","5230AWD71034","5230CGX16407","5230CGX16408","5230CGX16409","5230AWD71030"],"runtimes":["PT1M","PT1M","PT1M","PT1M","PT1M","PT7M","PT1M","PT3M","PT3M","PT0S","PT3M","PT0S","PT2M","PT2M","PT1M","PT5M","PT1M","PT1M","PT6M","PT0S","PT15M"],"activities":["pickUp","pickUpAndSetDown","pickUpAndSetDown","pickUpAndSetDown","pickUpAndSetDown","pickUpAndSetDown","pickUpAndSetDown","pickUpAndSetDown","pickUpAndSetDown","pickUpAndSetDown","pickUpAndSetDown","pickUpAndSetDown","pickUpAndSetDown","pickUpAndSetDown","pickUpAndSetDown","pickUpAndSetDown","pickUpAndSetDown","pickUpAndSetDown","pickUpAndSetDown","pickUpAndSetDown","pickUpAndSetDown","pickUpAndSetDown"],"waitTimes":["","","","","","","","","","","","","","","","","","","","","",""],"timingStatuses":["PTP","OTH","PTP","OTH","OTH","PTP","PTP","OTH","PTP","PTP","OTH","PTP","OTH","PTP","OTH","PTP","PTP","OTH","PTP","PTP","OTH","PTP"],"sequenceNumber":["1","2","3","4","5","6","7","8","9","10","11","12","13","14","15","16","22","23","24","25","30","31"],"dynamicDestinationDisplay":["","","","","","","","","","","","","","","","","","","","","",""],"lineId":"SL1","note":[],"vehicle":"","schedules":[{"profiles":{"regular":["Tuesday","Thursday"],"holidays":{"notRunning":["Christmas","GoodFriday","NewYearsDay","LateSummerBankHolidayNotScotland","MayDay","EasterMonday","SpringBank"]}},"departures":["14:05:00"],"dayShift":[0]}]}],"RT6":[{"destinationDisplay":"Aberystwyth Bus Station Stand 5","direction":"inbound","routeLinkId":["RL77","RL78","RL79","RL80","RL81","RL82","RL83","RL84","RL85","RL86","RL87","RL88","RL89","RL90","RL91","RL92","RL93","RL94","RL95"],"stopPoints":["5230AWD71032","5230AWD71033","5230CGX16417","5230WDB23421","5230CGX16406","5230CGX16423","5230WDB47547","5230AWD71044","5230AWD71047","5230CGX16415","5230AWD71050","5230AWD71051","5230AWD71053","5230AWD71054","5230WDB23416","5230AWD71056","5230WDB48336","5230WDB22901","5230AWD71097","5230WDB25330"],"runtimes":["PT4M","PT1M","PT3M","PT6M","PT1M","PT2M","PT4M","PT2M","PT3M","PT2M","PT9M","PT1M","PT0S","PT2M","PT1M","PT1M","PT1M","PT1M","PT1M"],"activities":["pickUp","pickUpAndSetDown","pickUpAndSetDown","pickUpAndSetDown","pickUpAndSetDown","pickUpAndSetDown","pickUpAndSetDown","pickUpAndSetDown","pickUpAndSetDown","pickUpAndSetDown","pickUpAndSetDown","pickUpAndSetDown","pickUpAndSetDown","pickUpAndSetDown","pickUpAndSetDown","pickUpAndSetDown","pickUpAndSetDown","pickUpAndSetDown","pickUpAndSetDown","pickUpAndSetDown"],"waitTimes":["","","","","","","","","","","","","","","","","","","",""],"timingStatuses":["PTP","PTP","OTH","PTP","OTH","PTP","PTP","OTH","PTP","OTH","PTP","PTP","OTH","OTH","OTH","PTP","OTH","OTH","OTH","PTP"],"sequenceNumber":["10","11","12","13","19","20","21","22","23","26","27","28","29","30","31","32","33","34","35","36"],"dynamicDestinationDisplay":["","","","","","","","","","","","","","","","","","","",""],"lineId":"SL1","note":[],"vehicle":"","schedules":[{"profiles":{"regular":["Tuesday","Thursday"],"holidays":{"notRunning":["Christmas","GoodFriday","NewYearsDay","LateSummerBankHolidayNotScotland","MayDay","EasterMonday","SpringBank"]}},"departures":["13:12:00"],"dayShift":[0]}]}],"RT7":[{"destinationDisplay":"Aberystwyth Bus Station Stand 5","direction":"inbound","routeLinkId":["RL96","RL97","RL98","RL99","RL100","RL101","RL102","RL103","RL104","RL105","RL106","RL107","RL108","RL109","RL110","RL111","RL112","RL113","RL114","RL115","RL116","RL117","RL118"],"stopPoints":["5230WDB23449","5230AWD71031","5230AWD71032","5230CGX16411","5230CGX16412","5230AWD71039","5230CGX16355","5230WDB23420","5230CGX16406","5230CGX16423","5230WDB47547","5230AWD71044","5230AWD71047","5230CGX16415","5230AWD71050","5230AWD71051","5230AWD71053","5230AWD71054","5230WDB23416","5230AWD71056","5230WDB48336","5230WDB22901","5230AWD71097","5230WDB25330"],"runtimes":["PT19M","PT1M","PT3M","PT7M","PT3M","PT2M","PT7M","PT1M","PT1M","PT2M","PT4M","PT2M","PT6M","PT4M","PT8M","PT1M","PT0S","PT2M","PT1M","PT2M","PT1M","PT0S","PT2M"],"activities":["pickUp","pickUpAndSetDown","pickUpAndSetDown","pickUpAndSetDown","pickUpAndSetDown","pickUpAndSetDown","pickUpAndSetDown","pickUpAndSetDown","pickUpAndSetDown","pickUpAndSetDown","pickUpAndSetDown","pickUpAndSetDown","pickUpAndSetDown","pickUpAndSetDown","pickUpAndSetDown","pickUpAndSetDown","pickUpAndSetDown","pickUpAndSetDown","pickUpAndSetDown","pickUpAndSetDown","pickUpAndSetDown","pickUpAndSetDown","pickUpAndSetDown","pickUpAndSetDown"],"waitTimes":["","","","","","","","","","","","","","","","","","","","","","","",""],"timingStatuses":["PTP","OTH","PTP","PTP","PTP","PTP","PTP","PTP","OTH","PTP","PTP","OTH","PTP","OTH","PTP","PTP","OTH","OTH","OTH","PTP","OTH","OTH","OTH","PTP"],"sequenceNumber":["3","4","10","14","15","16","17","18","19","20","21","22","23","26","27","28","29","30","31","32","33","34","35","36"],"dynamicDestinationDisplay":["","","","","","","","","","","","","","","","","","","","","","","",""],"lineId":"SL1","note":[],"vehicle":"","schedules":[{"profiles":{"regular":["Monday","Wednesday","Friday"],"holidays":{"notRunning":["Christmas","GoodFriday","NewYearsDay","LateSummerBankHolidayNotScotland","MayDay","EasterMonday","SpringBank"]}},"departures":["08:58:00"],"dayShift":[0]}]}],"RT8":[{"destinationDisplay":"Aberystwyth Bus Station Stand 5","direction":"inbound","routeLinkId":["RL119","RL120","RL121","RL122","RL123","RL124","RL125","RL126","RL127","RL128","RL129","RL130","RL131","RL132","RL133","RL134","RL135","RL136","RL137","RL138","RL139","RL140","RL141"],"stopPoints":["5230WDB23449","5230AWD71031","5230AWD71032","5230AWD71033","5230CGX16417","5230WDB23421","5230CGX16406","5230CGX16423","5230WDB47547","5230AWD71044","5230AWD71047","5230AWD71041","5230CGX16422","5230CGX16415","5230AWD71050","5230AWD71051","5230AWD71053","5230AWD71054","5230WDB23416","5230AWD71056","5230WDB48336","5230WDB22901","5230AWD71097","5230WDB25330"],"runtimes":["PT14M","PT1M","PT4M","PT1M","PT3M","PT6M","PT1M","PT2M","PT4M","PT2M","PT3M","PT3M","PT2M","PT2M","PT8M","PT1M","PT0S","PT2M","PT1M","PT2M","PT1M","PT0S","PT2M"],"activities":["pickUp","pickUpAndSetDown","pickUpAndSetDown","pickUpAndSetDown","pickUpAndSetDown","pickUpAndSetDown","pickUpAndSetDown","pickUpAndSetDown","pickUpAndSetDown","pickUpAndSetDown","pickUpAndSetDown","pickUpAndSetDown","pickUpAndSetDown","pickUpAndSetDown","pickUpAndSetDown","pickUpAndSetDown","pickUpAndSetDown","pickUpAndSetDown","pickUpAndSetDown","pickUpAndSetDown","pickUpAndSetDown","pickUpAndSetDown","pickUpAndSetDown","pickUpAndSetDown"],"waitTimes":["","","","","","","","","","","","","","","","","","","","","","","",""],"timingStatuses":["PTP","OTH","PTP","PTP","OTH","PTP","OTH","PTP","PTP","OTH","PTP","PTP","PTP","OTH","PTP","PTP","OTH","OTH","OTH","PTP","OTH","OTH","OTH","PTP"],"sequenceNumber":["3","4","10","11","12","13","19","20","21","22","23","24","25","26","27","28","29","30","31","32","33","34","35","36"],"dynamicDestinationDisplay":["","","","","","","","","","","","","","","","","","","","","","","",""],"lineId":"SL1","note":[],"vehicle":"","schedules":[{"profiles":{"regular":["Tuesday","Thursday"],"holidays":{"notRunning":["Christmas","GoodFriday","NewYearsDay","LateSummerBankHolidayNotScotland","MayDay","EasterMonday","SpringBank"]}},"departures":["09:12:00"],"dayShift":[0]}]}],"RT9":[{"destinationDisplay":"Aberystwyth Bus Station Stand 5","direction":"inbound","routeLinkId":["RL142","RL143","RL144","RL145","RL146","RL147","RL148","RL149","RL150","RL151","RL152","RL153","RL154","RL155","RL156","RL157","RL158","RL159","RL160","RL161","RL162","RL163","RL164","RL165"],"stopPoints":["5230AWD71034","5230CGX16407","5230CGX16408","5230AWD71032","5230CGX16411","5230CGX16412","5230AWD71039","5230CGX16355","5230WDB23420","5230CGX16406","5230CGX16423","5230WDB47547","5230AWD71044","5230AWD71047","5230CGX16415","5230AWD71050","5230AWD71051","5230AWD71053","5230AWD71054","5230WDB23416","5230AWD71056","5230WDB48336","5230WDB22901","5230AWD71097","5230WDB25330"],"runtimes":["PT3M","PT10M","PT1M","PT3M","PT7M","PT3M","PT3M","PT7M","PT0S","PT1M","PT2M","PT4M","PT2M","PT3M","PT2M","PT8M","PT1M","PT0S","PT2M","PT1M","PT2M","PT1M","PT0S","PT2M"],"activities":["pickUp","pickUpAndSetDown","pickUpAndSetDown","pickUpAndSetDown","pickUpAndSetDown","pickUpAndSetDown","pickUpAndSetDown","pickUpAndSetDown","pickUpAndSetDown","pickUpAndSetDown","pickUpAndSetDown","pickUpAndSetDown","pickUpAndSetDown","pickUpAndSetDown","pickUpAndSetDown","pickUpAndSetDown","pickUpAndSetDown","pickUpAndSetDown","pickUpAndSetDown","pickUpAndSetDown","pickUpAndSetDown","pickUpAndSetDown","pickUpAndSetDown","pickUpAndSetDown","pickUpAndSetDown"],"waitTimes":["","","","","","","","","","","","","","","","","","","","","","","","",""],"timingStatuses":["PTP","OTH","OTH","PTP","PTP","PTP","PTP","PTP","PTP","OTH","PTP","PTP","OTH","PTP","OTH","PTP","PTP","OTH","OTH","OTH","PTP","OTH","OTH","OTH","PTP"],"sequenceNumber":["7","8","9","10","14","15","16","17","18","19","20","21","22","23","26","27","28","29","30","31","32","33","34","35","36"],"dynamicDestinationDisplay":["","","","","","","","","","","","","","","","","","","","","","","","",""],"lineId":"SL1","note":[],"vehicle":"","schedules":[{"profiles":{"regular":["Monday","Wednesday","Friday"],"holidays":{"notRunning":["Christmas","GoodFriday","NewYearsDay","LateSummerBankHolidayNotScotland","MayDay","EasterMonday","SpringBank"]}},"departures":["12:46:00"],"dayShift":[0]}]}]},"vehicles":{"":{"description":""}},"servicedOrganisations":{"SDB":{"name":"Ceredigion","workingDays":[{"startDate":"2025-09-02","endDate":"2025-10-24","description":""},{"startDate":"2025-11-03","endDate":"2025-12-19","description":""},{"startDate":"2026-01-05","endDate":"2026-02-13","description":""},{"startDate":"2026-02-23","endDate":"2026-03-27","description":""},{"startDate":"2026-04-13","endDate":"2026-05-22","description":""},{"startDate":"2026-06-01","endDate":"2026-07-17","description":""},{"startDate":"2026-09-01","endDate":"2026-10-23","description":""}]}}}]}